[
  {
    "section": "Normal Moves",
    "name": "<td class=\"frame_fixed_m__icTnd frame_skill__tLJuM\"><span class=\"frame_arts__ZU5YI\">Standing Light Punch</span><p class=\"frame_classic___gpLR\"><img alt=\"\" src=\"assets/images/icons/icon_punch_l.png\"/>L</p></td>",
    "startup": "<td class=\"frame_startup_frame__Dc2Ph\">4</td>",
    "active": "<td class=\"frame_active_frame__6Sovc\"><p>4-6</p></td>",
    "recovery": "<td class=\"frame_recovery_frame__CznJj\">10</td>",
    "hitAdv": "<td class=\"frame_hit_frame__K7xOz undefined\">4</td>",
    "guardAdv": "<td class=\"frame_block_frame__SfHiW undefined\">-1</td>",
    "cancel": "<td class=\"frame_cancel__hT_hr\"><span class=\"frame_type_C__nVWNp\">C</span></td>",
    "damage": "<td class=\"frame_damage__HWaQm\">300 </td>",
    "comboMod": "<td class=\"frame_combo_correct__hCDUB\">Starter scaling 20%<br/></td>",
    "driveGain": "<td class=\"frame_drive_gauge_gain_hit___Jg7j\">250</td>",
    "driveLossGuard": "<td class=\"frame_drive_gauge_lose_dguard__4uQOc\">-500</td>",
    "driveLossPunish": "<td class=\"frame_drive_gauge_lose_punish__mFrmM\">-2000</td>",
    "saGain": "<td class=\"frame_sa_gauge_gain__oGcqw\">300</td>",
    "attribute": "<td class=\"frame_attribute__1vABD\">High</td>",
    "notes": "<td class=\"frame_note__hfwBr\"><p>Can be rapid canceled</p></td>"
  },
  {
    "section": "Normal Moves",
    "name": "<td class=\"frame_fixed_m__icTnd frame_skill__tLJuM\"><span class=\"frame_arts__ZU5YI\">Standing Light Kick</span><p class=\"frame_classic___gpLR\"><img alt=\"\" src=\"assets/images/icons/icon_kick_l.png\"/>L</p></td>",
    "startup": "<td class=\"frame_startup_frame__Dc2Ph\">5</td>",
    "active": "<td class=\"frame_active_frame__6Sovc\"><p>5-6</p></td>",
    "recovery": "<td class=\"frame_recovery_frame__CznJj\">12</td>",
    "hitAdv": "<td class=\"frame_hit_frame__K7xOz undefined\">2</td>",
    "guardAdv": "<td class=\"frame_block_frame__SfHiW undefined\">-2</td>",
    "cancel": "<td class=\"frame_cancel__hT_hr\"><span class=\"frame_type_C__nVWNp\">C</span></td>",
    "damage": "<td class=\"frame_damage__HWaQm\">300 </td>",
    "comboMod": "<td class=\"frame_combo_correct__hCDUB\">Starter scaling 20%<br/></td>",
    "driveGain": "<td class=\"frame_drive_gauge_gain_hit___Jg7j\">250</td>",
    "driveLossGuard": "<td class=\"frame_drive_gauge_lose_dguard__4uQOc\">-500</td>",
    "driveLossPunish": "<td class=\"frame_drive_gauge_lose_punish__mFrmM\">-2000</td>",
    "saGain": "<td class=\"frame_sa_gauge_gain__oGcqw\">300</td>",
    "attribute": "<td class=\"frame_attribute__1vABD\">High</td>",
    "notes": "<td class=\"frame_note__hfwBr\"></td>"
  },
  {
    "section": "Normal Moves",
    "name": "<td class=\"frame_fixed_m__icTnd frame_skill__tLJuM\"><span class=\"frame_arts__ZU5YI\">Standing Medium Punch</span><p class=\"frame_classic___gpLR\"><img alt=\"\" src=\"assets/images/icons/icon_punch_m.png\"/>M</p></td>",
    "startup": "<td class=\"frame_startup_frame__Dc2Ph\">7</td>",
    "active": "<td class=\"frame_active_frame__6Sovc\"><p>7-10</p></td>",
    "recovery": "<td class=\"frame_recovery_frame__CznJj\">15</td>",
    "hitAdv": "<td class=\"frame_hit_frame__K7xOz undefined\">2</td>",
    "guardAdv": "<td class=\"frame_block_frame__SfHiW undefined\">-2</td>",
    "cancel": "<td class=\"frame_cancel__hT_hr\"><span class=\"frame_type_C__nVWNp\">C</span></td>",
    "damage": "<td class=\"frame_damage__HWaQm\">600 </td>",
    "comboMod": "<td class=\"frame_combo_correct__hCDUB\"></td>",
    "driveGain": "<td class=\"frame_drive_gauge_gain_hit___Jg7j\">1500</td>",
    "driveLossGuard": "<td class=\"frame_drive_gauge_lose_dguard__4uQOc\">-3000</td>",
    "driveLossPunish": "<td class=\"frame_drive_gauge_lose_punish__mFrmM\">-4000</td>",
    "saGain": "<td class=\"frame_sa_gauge_gain__oGcqw\">500</td>",
    "attribute": "<td class=\"frame_attribute__1vABD\">High</td>",
    "notes": "<td class=\"frame_note__hfwBr\"></td>"
  },
  {
    "section": "Normal Moves",
    "name": "<td class=\"frame_fixed_m__icTnd frame_skill__tLJuM\"><span class=\"frame_arts__ZU5YI\">Standing Medium Kick</span><p class=\"frame_classic___gpLR\"><img alt=\"\" src=\"assets/images/icons/icon_kick_m.png\"/>M</p></td>",
    "startup": "<td class=\"frame_startup_frame__Dc2Ph\">10</td>",
    "active": "<td class=\"frame_active_frame__6Sovc\"><p>10-12</p></td>",
    "recovery": "<td class=\"frame_recovery_frame__CznJj\">18</td>",
    "hitAdv": "<td class=\"frame_hit_frame__K7xOz undefined\">-2</td>",
    "guardAdv": "<td class=\"frame_block_frame__SfHiW undefined\">-5</td>",
    "cancel": "<td class=\"frame_cancel__hT_hr\"><span class=\"frame_type_C__nVWNp\">C</span></td>",
    "damage": "<td class=\"frame_damage__HWaQm\">600 </td>",
    "comboMod": "<td class=\"frame_combo_correct__hCDUB\"></td>",
    "driveGain": "<td class=\"frame_drive_gauge_gain_hit___Jg7j\">1500</td>",
    "driveLossGuard": "<td class=\"frame_drive_gauge_lose_dguard__4uQOc\">-3000</td>",
    "driveLossPunish": "<td class=\"frame_drive_gauge_lose_punish__mFrmM\">-4000</td>",
    "saGain": "<td class=\"frame_sa_gauge_gain__oGcqw\">700</td>",
    "attribute": "<td class=\"frame_attribute__1vABD\">High</td>",
    "notes": "<td class=\"frame_note__hfwBr\"></td>"
  },
  {
    "section": "Normal Moves",
    "name": "<td class=\"frame_fixed_m__icTnd frame_skill__tLJuM\"><span class=\"frame_arts__ZU5YI\">Standing Heavy Punch</span><p class=\"frame_classic___gpLR\"><img alt=\"\" src=\"assets/images/icons/icon_punch_h.png\"/>H</p></td>",
    "startup": "<td class=\"frame_startup_frame__Dc2Ph\">10</td>",
    "active": "<td class=\"frame_active_frame__6Sovc\"><p>10-13</p></td>",
    "recovery": "<td class=\"frame_recovery_frame__CznJj\">20</td>",
    "hitAdv": "<td class=\"frame_hit_frame__K7xOz\">0</td>",
    "guardAdv": "<td class=\"frame_block_frame__SfHiW undefined\">-3</td>",
    "cancel": "<td class=\"frame_cancel__hT_hr\"><span class=\"frame_type_SA__bp6SJ\">SA</span></td>",
    "damage": "<td class=\"frame_damage__HWaQm\">800 </td>",
    "comboMod": "<td class=\"frame_combo_correct__hCDUB\"></td>",
    "driveGain": "<td class=\"frame_drive_gauge_gain_hit___Jg7j\">3000</td>",
    "driveLossGuard": "<td class=\"frame_drive_gauge_lose_dguard__4uQOc\">-6000</td>",
    "driveLossPunish": "<td class=\"frame_drive_gauge_lose_punish__mFrmM\">-10000</td>",
    "saGain": "<td class=\"frame_sa_gauge_gain__oGcqw\">1000</td>",
    "attribute": "<td class=\"frame_attribute__1vABD\">High</td>",
    "notes": "<td class=\"frame_note__hfwBr\"><p>Forces a juggle state when hitting a mid-air opponent</p></td>"
  },
  {
    "section": "Normal Moves",
    "name": "<td class=\"frame_fixed_m__icTnd frame_skill__tLJuM\"><span class=\"frame_arts__ZU5YI\">Standing Heavy Kick</span><p class=\"frame_classic___gpLR\"><img alt=\"\" src=\"assets/images/icons/icon_kick_h.png\"/>H</p></td>",
    "startup": "<td class=\"frame_startup_frame__Dc2Ph\">15</td>",
    "active": "<td class=\"frame_active_frame__6Sovc\"><p>15-17</p></td>",
    "recovery": "<td class=\"frame_recovery_frame__CznJj\">26</td>",
    "hitAdv": "<td class=\"frame_hit_frame__K7xOz\">※1</td>",
    "guardAdv": "<td class=\"frame_block_frame__SfHiW undefined\">-6</td>",
    "cancel": "<td class=\"frame_cancel__hT_hr\"></td>",
    "damage": "<td class=\"frame_damage__HWaQm\">900 </td>",
    "comboMod": "<td class=\"frame_combo_correct__hCDUB\"></td>",
    "driveGain": "<td class=\"frame_drive_gauge_gain_hit___Jg7j\">3000</td>",
    "driveLossGuard": "<td class=\"frame_drive_gauge_lose_dguard__4uQOc\">-6000</td>",
    "driveLossPunish": "<td class=\"frame_drive_gauge_lose_punish__mFrmM\">-10000</td>",
    "saGain": "<td class=\"frame_sa_gauge_gain__oGcqw\">1000</td>",
    "attribute": "<td class=\"frame_attribute__1vABD\">High</td>",
    "notes": "<td class=\"frame_note__hfwBr\"><p>* Adds +17 frames of advantage on a standing opponent during a Punish Counter<br/>Forces a juggle state when hitting a mid-air opponent for a Punish Counter</p></td>"
  },
  {
    "section": "Normal Moves",
    "name": "<td class=\"frame_fixed_m__icTnd frame_skill__tLJuM\"><span class=\"frame_arts__ZU5YI\">Crouching Light Punch</span><p class=\"frame_classic___gpLR\"><img alt=\"\" src=\"assets/images/icons/key-d.png\"/> <img alt=\"\" src=\"assets/images/icons/key-plus.png\"/> <img alt=\"\" src=\"assets/images/icons/icon_punch_l.png\"/>L</p></td>",
    "startup": "<td class=\"frame_startup_frame__Dc2Ph\">4</td>",
    "active": "<td class=\"frame_active_frame__6Sovc\"><p>4-5</p></td>",
    "recovery": "<td class=\"frame_recovery_frame__CznJj\">11</td>",
    "hitAdv": "<td class=\"frame_hit_frame__K7xOz undefined\">3</td>",
    "guardAdv": "<td class=\"frame_block_frame__SfHiW undefined\">-2</td>",
    "cancel": "<td class=\"frame_cancel__hT_hr\"><span class=\"frame_type_C__nVWNp\">C</span></td>",
    "damage": "<td class=\"frame_damage__HWaQm\">300 </td>",
    "comboMod": "<td class=\"frame_combo_correct__hCDUB\">Starter scaling 20%<br/></td>",
    "driveGain": "<td class=\"frame_drive_gauge_gain_hit___Jg7j\">250</td>",
    "driveLossGuard": "<td class=\"frame_drive_gauge_lose_dguard__4uQOc\">-500</td>",
    "driveLossPunish": "<td class=\"frame_drive_gauge_lose_punish__mFrmM\">-2000</td>",
    "saGain": "<td class=\"frame_sa_gauge_gain__oGcqw\">300</td>",
    "attribute": "<td class=\"frame_attribute__1vABD\">High</td>",
    "notes": "<td class=\"frame_note__hfwBr\"><p>Can be rapid canceled</p></td>"
  },
  {
    "section": "Normal Moves",
    "name": "<td class=\"frame_fixed_m__icTnd frame_skill__tLJuM\"><span class=\"frame_arts__ZU5YI\">Crouching Light Kick</span><p class=\"frame_classic___gpLR\"><img alt=\"\" src=\"assets/images/icons/key-d.png\"/> <img alt=\"\" src=\"assets/images/icons/key-plus.png\"/> <img alt=\"\" src=\"assets/images/icons/icon_kick_l.png\"/>L</p></td>",
    "startup": "<td class=\"frame_startup_frame__Dc2Ph\">5</td>",
    "active": "<td class=\"frame_active_frame__6Sovc\"><p>5-6</p></td>",
    "recovery": "<td class=\"frame_recovery_frame__CznJj\">13</td>",
    "hitAdv": "<td class=\"frame_hit_frame__K7xOz undefined\">-1</td>",
    "guardAdv": "<td class=\"frame_block_frame__SfHiW undefined\">-3</td>",
    "cancel": "<td class=\"frame_cancel__hT_hr\"></td>",
    "damage": "<td class=\"frame_damage__HWaQm\">200 </td>",
    "comboMod": "<td class=\"frame_combo_correct__hCDUB\">Starter scaling 20%<br/></td>",
    "driveGain": "<td class=\"frame_drive_gauge_gain_hit___Jg7j\">250</td>",
    "driveLossGuard": "<td class=\"frame_drive_gauge_lose_dguard__4uQOc\">-500</td>",
    "driveLossPunish": "<td class=\"frame_drive_gauge_lose_punish__mFrmM\">-2000</td>",
    "saGain": "<td class=\"frame_sa_gauge_gain__oGcqw\">300</td>",
    "attribute": "<td class=\"frame_attribute__1vABD\">Low</td>",
    "notes": "<td class=\"frame_note__hfwBr\"><p>Can be rapid canceled</p></td>"
  },
  {
    "section": "Normal Moves",
    "name": "<td class=\"frame_fixed_m__icTnd frame_skill__tLJuM\"><span class=\"frame_arts__ZU5YI\">Crouching Medium Punch</span><p class=\"frame_classic___gpLR\"><img alt=\"\" src=\"assets/images/icons/key-d.png\"/> <img alt=\"\" src=\"assets/images/icons/key-plus.png\"/> <img alt=\"\" src=\"assets/images/icons/icon_punch_m.png\"/>M</p></td>",
    "startup": "<td class=\"frame_startup_frame__Dc2Ph\">7</td>",
    "active": "<td class=\"frame_active_frame__6Sovc\"><p>7-9</p></td>",
    "recovery": "<td class=\"frame_recovery_frame__CznJj\">11</td>",
    "hitAdv": "<td class=\"frame_hit_frame__K7xOz undefined\">6</td>",
    "guardAdv": "<td class=\"frame_block_frame__SfHiW undefined\">-1</td>",
    "cancel": "<td class=\"frame_cancel__hT_hr\"><span class=\"frame_type_C__nVWNp\">C</span></td>",
    "damage": "<td class=\"frame_damage__HWaQm\">600 </td>",
    "comboMod": "<td class=\"frame_combo_correct__hCDUB\"></td>",
    "driveGain": "<td class=\"frame_drive_gauge_gain_hit___Jg7j\">1500</td>",
    "driveLossGuard": "<td class=\"frame_drive_gauge_lose_dguard__4uQOc\">-3000</td>",
    "driveLossPunish": "<td class=\"frame_drive_gauge_lose_punish__mFrmM\">-4000</td>",
    "saGain": "<td class=\"frame_sa_gauge_gain__oGcqw\">500</td>",
    "attribute": "<td class=\"frame_attribute__1vABD\">High</td>",
    "notes": "<td class=\"frame_note__hfwBr\"><p>4 frames of recovery added when the attack misses</p></td>"
  },
  {
    "section": "Normal Moves",
    "name": "<td class=\"frame_fixed_m__icTnd frame_skill__tLJuM\"><span class=\"frame_arts__ZU5YI\">Crouching Medium Kick</span><p class=\"frame_classic___gpLR\"><img alt=\"\" src=\"assets/images/icons/key-d.png\"/> <img alt=\"\" src=\"assets/images/icons/key-plus.png\"/> <img alt=\"\" src=\"assets/images/icons/icon_kick_m.png\"/>M</p></td>",
    "startup": "<td class=\"frame_startup_frame__Dc2Ph\">8</td>",
    "active": "<td class=\"frame_active_frame__6Sovc\"><p>8-11</p></td>",
    "recovery": "<td class=\"frame_recovery_frame__CznJj\">16</td>",
    "hitAdv": "<td class=\"frame_hit_frame__K7xOz undefined\">3</td>",
    "guardAdv": "<td class=\"frame_block_frame__SfHiW undefined\">-2</td>",
    "cancel": "<td class=\"frame_cancel__hT_hr\"></td>",
    "damage": "<td class=\"frame_damage__HWaQm\">600 </td>",
    "comboMod": "<td class=\"frame_combo_correct__hCDUB\">Starter scaling 20%<br/></td>",
    "driveGain": "<td class=\"frame_drive_gauge_gain_hit___Jg7j\">2000</td>",
    "driveLossGuard": "<td class=\"frame_drive_gauge_lose_dguard__4uQOc\">-4000</td>",
    "driveLossPunish": "<td class=\"frame_drive_gauge_lose_punish__mFrmM\">-6000</td>",
    "saGain": "<td class=\"frame_sa_gauge_gain__oGcqw\">600</td>",
    "attribute": "<td class=\"frame_attribute__1vABD\">Low</td>",
    "notes": "<td class=\"frame_note__hfwBr\"></td>"
  },
  {
    "section": "Normal Moves",
    "name": "<td class=\"frame_fixed_m__icTnd frame_skill__tLJuM\"><span class=\"frame_arts__ZU5YI\">Crouching Heavy Punch</span><p class=\"frame_classic___gpLR\"><img alt=\"\" src=\"assets/images/icons/key-d.png\"/> <img alt=\"\" src=\"assets/images/icons/key-plus.png\"/> <img alt=\"\" src=\"assets/images/icons/icon_punch_h.png\"/>H</p></td>",
    "startup": "<td class=\"frame_startup_frame__Dc2Ph\">10</td>",
    "active": "<td class=\"frame_active_frame__6Sovc\"><p>10-14</p></td>",
    "recovery": "<td class=\"frame_recovery_frame__CznJj\">21</td>",
    "hitAdv": "<td class=\"frame_hit_frame__K7xOz undefined\">-2</td>",
    "guardAdv": "<td class=\"frame_block_frame__SfHiW undefined\">-8</td>",
    "cancel": "<td class=\"frame_cancel__hT_hr\"></td>",
    "damage": "<td class=\"frame_damage__HWaQm\">600 </td>",
    "comboMod": "<td class=\"frame_combo_correct__hCDUB\"></td>",
    "driveGain": "<td class=\"frame_drive_gauge_gain_hit___Jg7j\">3000</td>",
    "driveLossGuard": "<td class=\"frame_drive_gauge_lose_dguard__4uQOc\">-6000</td>",
    "driveLossPunish": "<td class=\"frame_drive_gauge_lose_punish__mFrmM\">-10000</td>",
    "saGain": "<td class=\"frame_sa_gauge_gain__oGcqw\">1000</td>",
    "attribute": "<td class=\"frame_attribute__1vABD\">High</td>",
    "notes": "<td class=\"frame_note__hfwBr\"></td>"
  },
  {
    "section": "Normal Moves",
    "name": "<td class=\"frame_fixed_m__icTnd frame_skill__tLJuM\"><span class=\"frame_arts__ZU5YI\">Crouching Heavy Kick</span><p class=\"frame_classic___gpLR\"><img alt=\"\" src=\"assets/images/icons/key-d.png\"/> <img alt=\"\" src=\"assets/images/icons/key-plus.png\"/> <img alt=\"\" src=\"assets/images/icons/icon_kick_h.png\"/>H</p></td>",
    "startup": "<td class=\"frame_startup_frame__Dc2Ph\">11</td>",
    "active": "<td class=\"frame_active_frame__6Sovc\"><p>11-12</p></td>",
    "recovery": "<td class=\"frame_recovery_frame__CznJj\">27</td>",
    "hitAdv": "<td class=\"frame_hit_frame__K7xOz\">D</td>",
    "guardAdv": "<td class=\"frame_block_frame__SfHiW undefined\">-12</td>",
    "cancel": "<td class=\"frame_cancel__hT_hr\"></td>",
    "damage": "<td class=\"frame_damage__HWaQm\">900 </td>",
    "comboMod": "<td class=\"frame_combo_correct__hCDUB\"></td>",
    "driveGain": "<td class=\"frame_drive_gauge_gain_hit___Jg7j\">3000</td>",
    "driveLossGuard": "<td class=\"frame_drive_gauge_lose_dguard__4uQOc\">-4000</td>",
    "driveLossPunish": "<td class=\"frame_drive_gauge_lose_punish__mFrmM\">-10000</td>",
    "saGain": "<td class=\"frame_sa_gauge_gain__oGcqw\">1000</td>",
    "attribute": "<td class=\"frame_attribute__1vABD\">Low</td>",
    "notes": "<td class=\"frame_note__hfwBr\"><p>Knockdown time extended when the attack lands as a Punish Counter, and changes to Hard Knockdown</p></td>"
  },
  {
    "section": "Normal Moves",
    "name": "<td class=\"frame_fixed_m__icTnd frame_skill__tLJuM\"><span class=\"frame_arts__ZU5YI\">Jumping Light Punch</span><p class=\"frame_classic___gpLR\">(During a jump) <img alt=\"\" src=\"assets/images/icons/icon_punch_l.png\"/>L</p></td>",
    "startup": "<td class=\"frame_startup_frame__Dc2Ph\">5</td>",
    "active": "<td class=\"frame_active_frame__6Sovc\"><p>5-14</p></td>",
    "recovery": "<td class=\"frame_recovery_frame__CznJj\">3 frame(s) after landing</td>",
    "hitAdv": "<td class=\"frame_hit_frame__K7xOz\"></td>",
    "guardAdv": "<td class=\"frame_block_frame__SfHiW\"></td>",
    "cancel": "<td class=\"frame_cancel__hT_hr\"></td>",
    "damage": "<td class=\"frame_damage__HWaQm\">300 </td>",
    "comboMod": "<td class=\"frame_combo_correct__hCDUB\"></td>",
    "driveGain": "<td class=\"frame_drive_gauge_gain_hit___Jg7j\">500</td>",
    "driveLossGuard": "<td class=\"frame_drive_gauge_lose_dguard__4uQOc\">-1500</td>",
    "driveLossPunish": "<td class=\"frame_drive_gauge_lose_punish__mFrmM\">-2000</td>",
    "saGain": "<td class=\"frame_sa_gauge_gain__oGcqw\">300</td>",
    "attribute": "<td class=\"frame_attribute__1vABD\">Mid</td>",
    "notes": "<td class=\"frame_note__hfwBr\"></td>"
  },
  {
    "section": "Normal Moves",
    "name": "<td class=\"frame_fixed_m__icTnd frame_skill__tLJuM\"><span class=\"frame_arts__ZU5YI\">Jumping Light Kick</span><p class=\"frame_classic___gpLR\">(During a jump) <img alt=\"\" src=\"assets/images/icons/icon_kick_l.png\"/>L</p></td>",
    "startup": "<td class=\"frame_startup_frame__Dc2Ph\">6</td>",
    "active": "<td class=\"frame_active_frame__6Sovc\"><p>6-14</p></td>",
    "recovery": "<td class=\"frame_recovery_frame__CznJj\">3 frame(s) after landing</td>",
    "hitAdv": "<td class=\"frame_hit_frame__K7xOz\"></td>",
    "guardAdv": "<td class=\"frame_block_frame__SfHiW\"></td>",
    "cancel": "<td class=\"frame_cancel__hT_hr\"></td>",
    "damage": "<td class=\"frame_damage__HWaQm\">300 </td>",
    "comboMod": "<td class=\"frame_combo_correct__hCDUB\"></td>",
    "driveGain": "<td class=\"frame_drive_gauge_gain_hit___Jg7j\">500</td>",
    "driveLossGuard": "<td class=\"frame_drive_gauge_lose_dguard__4uQOc\">-1500</td>",
    "driveLossPunish": "<td class=\"frame_drive_gauge_lose_punish__mFrmM\">-2000</td>",
    "saGain": "<td class=\"frame_sa_gauge_gain__oGcqw\">300</td>",
    "attribute": "<td class=\"frame_attribute__1vABD\">Mid</td>",
    "notes": "<td class=\"frame_note__hfwBr\"><p>Has cross-up attack properties</p></td>"
  },
  {
    "section": "Normal Moves",
    "name": "<td class=\"frame_fixed_m__icTnd frame_skill__tLJuM\"><span class=\"frame_arts__ZU5YI\">Jumping Medium Punch</span><p class=\"frame_classic___gpLR\">(During a jump) <img alt=\"\" src=\"assets/images/icons/icon_punch_m.png\"/>M</p></td>",
    "startup": "<td class=\"frame_startup_frame__Dc2Ph\">8</td>",
    "active": "<td class=\"frame_active_frame__6Sovc\"><p>8-11</p></td>",
    "recovery": "<td class=\"frame_recovery_frame__CznJj\">3 frame(s) after landing</td>",
    "hitAdv": "<td class=\"frame_hit_frame__K7xOz\"></td>",
    "guardAdv": "<td class=\"frame_block_frame__SfHiW\"></td>",
    "cancel": "<td class=\"frame_cancel__hT_hr\"></td>",
    "damage": "<td class=\"frame_damage__HWaQm\">700 </td>",
    "comboMod": "<td class=\"frame_combo_correct__hCDUB\"></td>",
    "driveGain": "<td class=\"frame_drive_gauge_gain_hit___Jg7j\">1000</td>",
    "driveLossGuard": "<td class=\"frame_drive_gauge_lose_dguard__4uQOc\">-2500</td>",
    "driveLossPunish": "<td class=\"frame_drive_gauge_lose_punish__mFrmM\">-4000</td>",
    "saGain": "<td class=\"frame_sa_gauge_gain__oGcqw\">500</td>",
    "attribute": "<td class=\"frame_attribute__1vABD\">Mid</td>",
    "notes": "<td class=\"frame_note__hfwBr\"><p>Forces a juggle state when hitting a mid-air opponent</p></td>"
  },
  {
    "section": "Normal Moves",
    "name": "<td class=\"frame_fixed_m__icTnd frame_skill__tLJuM\"><span class=\"frame_arts__ZU5YI\">Jumping Medium Kick</span><p class=\"frame_classic___gpLR\">(During a jump) <img alt=\"\" src=\"assets/images/icons/icon_kick_m.png\"/>M</p></td>",
    "startup": "<td class=\"frame_startup_frame__Dc2Ph\">7</td>",
    "active": "<td class=\"frame_active_frame__6Sovc\"><p>7-12</p></td>",
    "recovery": "<td class=\"frame_recovery_frame__CznJj\">3 frame(s) after landing</td>",
    "hitAdv": "<td class=\"frame_hit_frame__K7xOz\"></td>",
    "guardAdv": "<td class=\"frame_block_frame__SfHiW\"></td>",
    "cancel": "<td class=\"frame_cancel__hT_hr\"></td>",
    "damage": "<td class=\"frame_damage__HWaQm\">500 </td>",
    "comboMod": "<td class=\"frame_combo_correct__hCDUB\"></td>",
    "driveGain": "<td class=\"frame_drive_gauge_gain_hit___Jg7j\">1000</td>",
    "driveLossGuard": "<td class=\"frame_drive_gauge_lose_dguard__4uQOc\">-2500</td>",
    "driveLossPunish": "<td class=\"frame_drive_gauge_lose_punish__mFrmM\">-4000</td>",
    "saGain": "<td class=\"frame_sa_gauge_gain__oGcqw\">500</td>",
    "attribute": "<td class=\"frame_attribute__1vABD\">Mid</td>",
    "notes": "<td class=\"frame_note__hfwBr\"><p>Has cross-up attack properties</p></td>"
  },
  {
    "section": "Normal Moves",
    "name": "<td class=\"frame_fixed_m__icTnd frame_skill__tLJuM\"><span class=\"frame_arts__ZU5YI\">Jumping Heavy Punch</span><p class=\"frame_classic___gpLR\">(During a jump) <img alt=\"\" src=\"assets/images/icons/icon_punch_h.png\"/>H</p></td>",
    "startup": "<td class=\"frame_startup_frame__Dc2Ph\">9</td>",
    "active": "<td class=\"frame_active_frame__6Sovc\"><p>9-12</p></td>",
    "recovery": "<td class=\"frame_recovery_frame__CznJj\">3 frame(s) after landing</td>",
    "hitAdv": "<td class=\"frame_hit_frame__K7xOz\"></td>",
    "guardAdv": "<td class=\"frame_block_frame__SfHiW\"></td>",
    "cancel": "<td class=\"frame_cancel__hT_hr\"></td>",
    "damage": "<td class=\"frame_damage__HWaQm\">800 </td>",
    "comboMod": "<td class=\"frame_combo_correct__hCDUB\"></td>",
    "driveGain": "<td class=\"frame_drive_gauge_gain_hit___Jg7j\">2000</td>",
    "driveLossGuard": "<td class=\"frame_drive_gauge_lose_dguard__4uQOc\">-4000</td>",
    "driveLossPunish": "<td class=\"frame_drive_gauge_lose_punish__mFrmM\">-5000</td>",
    "saGain": "<td class=\"frame_sa_gauge_gain__oGcqw\">1000</td>",
    "attribute": "<td class=\"frame_attribute__1vABD\">Mid</td>",
    "notes": "<td class=\"frame_note__hfwBr\"><p>Forces a slam knockdown when hitting a mid-air opponent</p></td>"
  },
  {
    "section": "Normal Moves",
    "name": "<td class=\"frame_fixed_m__icTnd frame_skill__tLJuM\"><span class=\"frame_arts__ZU5YI\">Jumping Heavy Kick</span><p class=\"frame_classic___gpLR\">(During a jump) <img alt=\"\" src=\"assets/images/icons/icon_kick_h.png\"/>H</p></td>",
    "startup": "<td class=\"frame_startup_frame__Dc2Ph\">11</td>",
    "active": "<td class=\"frame_active_frame__6Sovc\"><p>11-15</p></td>",
    "recovery": "<td class=\"frame_recovery_frame__CznJj\">3 frame(s) after landing</td>",
    "hitAdv": "<td class=\"frame_hit_frame__K7xOz\"></td>",
    "guardAdv": "<td class=\"frame_block_frame__SfHiW\"></td>",
    "cancel": "<td class=\"frame_cancel__hT_hr\"></td>",
    "damage": "<td class=\"frame_damage__HWaQm\">800 </td>",
    "comboMod": "<td class=\"frame_combo_correct__hCDUB\"></td>",
    "driveGain": "<td class=\"frame_drive_gauge_gain_hit___Jg7j\">2000</td>",
    "driveLossGuard": "<td class=\"frame_drive_gauge_lose_dguard__4uQOc\">-4000</td>",
    "driveLossPunish": "<td class=\"frame_drive_gauge_lose_punish__mFrmM\">-5000</td>",
    "saGain": "<td class=\"frame_sa_gauge_gain__oGcqw\">1000</td>",
    "attribute": "<td class=\"frame_attribute__1vABD\">Mid</td>",
    "notes": "<td class=\"frame_note__hfwBr\"></td>"
  },
  {
    "section": "Unique Attacks",
    "name": "<td class=\"frame_fixed_m__icTnd frame_skill__tLJuM\"><span class=\"frame_arts__ZU5YI\">Révérence</span><p class=\"frame_classic___gpLR\"><img alt=\"\" src=\"assets/images/icons/key-l.png\"/> <img alt=\"\" src=\"assets/images/icons/key-plus.png\"/> <img alt=\"\" src=\"assets/images/icons/icon_punch_h.png\"/>H</p></td>",
    "startup": "<td class=\"frame_startup_frame__Dc2Ph\">8</td>",
    "active": "<td class=\"frame_active_frame__6Sovc\"><p>8-13</p></td>",
    "recovery": "<td class=\"frame_recovery_frame__CznJj\">17</td>",
    "hitAdv": "<td class=\"frame_hit_frame__K7xOz undefined\">3</td>",
    "guardAdv": "<td class=\"frame_block_frame__SfHiW undefined\">1</td>",
    "cancel": "<td class=\"frame_cancel__hT_hr\"><span class=\"frame_type_C__nVWNp\">C</span></td>",
    "damage": "<td class=\"frame_damage__HWaQm\">800 </td>",
    "comboMod": "<td class=\"frame_combo_correct__hCDUB\"></td>",
    "driveGain": "<td class=\"frame_drive_gauge_gain_hit___Jg7j\">2000</td>",
    "driveLossGuard": "<td class=\"frame_drive_gauge_lose_dguard__4uQOc\">-5000</td>",
    "driveLossPunish": "<td class=\"frame_drive_gauge_lose_punish__mFrmM\">-8000</td>",
    "saGain": "<td class=\"frame_sa_gauge_gain__oGcqw\">1000</td>",
    "attribute": "<td class=\"frame_attribute__1vABD\">High</td>",
    "notes": "<td class=\"frame_note__hfwBr\"><p>Forces a juggle state when hitting a mid-air opponent</p></td>"
  },
  {
    "section": "Unique Attacks",
    "name": "<td class=\"frame_fixed_m__icTnd frame_skill__tLJuM\"><span class=\"frame_arts__ZU5YI\">Tomoe Derrière</span><p class=\"frame_classic___gpLR\"><img alt=\"\" src=\"assets/images/icons/key-dr.png\"/> <img alt=\"\" src=\"assets/images/icons/key-plus.png\"/> <img alt=\"\" src=\"assets/images/icons/icon_kick_h.png\"/>H</p></td>",
    "startup": "<td class=\"frame_startup_frame__Dc2Ph\">11</td>",
    "active": "<td class=\"frame_active_frame__6Sovc\"><p>11-19</p></td>",
    "recovery": "<td class=\"frame_recovery_frame__CznJj\">32</td>",
    "hitAdv": "<td class=\"frame_hit_frame__K7xOz undefined\">26</td>",
    "guardAdv": "<td class=\"frame_block_frame__SfHiW undefined\">-23</td>",
    "cancel": "<td class=\"frame_cancel__hT_hr\"></td>",
    "damage": "<td class=\"frame_damage__HWaQm\">1000 </td>",
    "comboMod": "<td class=\"frame_combo_correct__hCDUB\"></td>",
    "driveGain": "<td class=\"frame_drive_gauge_gain_hit___Jg7j\">3000</td>",
    "driveLossGuard": "<td class=\"frame_drive_gauge_lose_dguard__4uQOc\">-6000</td>",
    "driveLossPunish": "<td class=\"frame_drive_gauge_lose_punish__mFrmM\">-10000</td>",
    "saGain": "<td class=\"frame_sa_gauge_gain__oGcqw\">500</td>",
    "attribute": "<td class=\"frame_attribute__1vABD\">High</td>",
    "notes": "<td class=\"frame_note__hfwBr\"><p>juggle state changes when attack lands as a Punish Counter on a grounded opponent<br/>Forces a juggle state when the attack lands as a Punish Counter on a mid-air opponent</p></td>"
  },
  {
    "section": "Unique Attacks",
    "name": "<td class=\"frame_fixed_m__icTnd frame_skill__tLJuM\"><span class=\"frame_arts__ZU5YI\">À Terre</span><p class=\"frame_classic___gpLR\"><img alt=\"\" src=\"assets/images/icons/icon_punch_m.png\"/>M<img alt=\"\" src=\"assets/images/icons/arrow_3.png\"/><img alt=\"\" src=\"assets/images/icons/icon_kick_m.png\"/>M</p></td>",
    "startup": "<td class=\"frame_startup_frame__Dc2Ph\">10</td>",
    "active": "<td class=\"frame_active_frame__6Sovc\"><p>10-11</p></td>",
    "recovery": "<td class=\"frame_recovery_frame__CznJj\">17</td>",
    "hitAdv": "<td class=\"frame_hit_frame__K7xOz undefined\">2</td>",
    "guardAdv": "<td class=\"frame_block_frame__SfHiW undefined\">-5</td>",
    "cancel": "<td class=\"frame_cancel__hT_hr\"></td>",
    "damage": "<td class=\"frame_damage__HWaQm\">500 </td>",
    "comboMod": "<td class=\"frame_combo_correct__hCDUB\"></td>",
    "driveGain": "<td class=\"frame_drive_gauge_gain_hit___Jg7j\">2500</td>",
    "driveLossGuard": "<td class=\"frame_drive_gauge_lose_dguard__4uQOc\">-2500</td>",
    "driveLossPunish": "<td class=\"frame_drive_gauge_lose_punish__mFrmM\">-4000</td>",
    "saGain": "<td class=\"frame_sa_gauge_gain__oGcqw\">700</td>",
    "attribute": "<td class=\"frame_attribute__1vABD\">High</td>",
    "notes": "<td class=\"frame_note__hfwBr\"><p>Knockdown when standing medium punch lands as a Punish Counter.</p></td>"
  },
  {
    "section": "Unique Attacks",
    "name": "<td class=\"frame_fixed_m__icTnd frame_skill__tLJuM\"><span class=\"frame_arts__ZU5YI\">En Haut(1)</span><p class=\"frame_classic___gpLR\"><img alt=\"\" src=\"assets/images/icons/key-l.png\"/> <img alt=\"\" src=\"assets/images/icons/key-plus.png\"/> <img alt=\"\" src=\"assets/images/icons/icon_kick_m.png\"/>M</p></td>",
    "startup": "<td class=\"frame_startup_frame__Dc2Ph\">10</td>",
    "active": "<td class=\"frame_active_frame__6Sovc\"><p>10-13</p></td>",
    "recovery": "<td class=\"frame_recovery_frame__CznJj\">19</td>",
    "hitAdv": "<td class=\"frame_hit_frame__K7xOz undefined\">-1</td>",
    "guardAdv": "<td class=\"frame_block_frame__SfHiW undefined\">-3</td>",
    "cancel": "<td class=\"frame_cancel__hT_hr\"></td>",
    "damage": "<td class=\"frame_damage__HWaQm\">600 </td>",
    "comboMod": "<td class=\"frame_combo_correct__hCDUB\"></td>",
    "driveGain": "<td class=\"frame_drive_gauge_gain_hit___Jg7j\">2000</td>",
    "driveLossGuard": "<td class=\"frame_drive_gauge_lose_dguard__4uQOc\">-4000</td>",
    "driveLossPunish": "<td class=\"frame_drive_gauge_lose_punish__mFrmM\">-4000</td>",
    "saGain": "<td class=\"frame_sa_gauge_gain__oGcqw\">700</td>",
    "attribute": "<td class=\"frame_attribute__1vABD\">High</td>",
    "notes": "<td class=\"frame_note__hfwBr\"><p>Forces a juggle state when hitting a mid-air opponent</p></td>"
  },
  {
    "section": "Unique Attacks",
    "name": "<td class=\"frame_fixed_m__icTnd frame_skill__tLJuM\"><span class=\"frame_arts__ZU5YI\">En Haut(2)</span><p class=\"frame_classic___gpLR\"><img alt=\"\" src=\"assets/images/icons/key-l.png\"/> <img alt=\"\" src=\"assets/images/icons/key-plus.png\"/> <img alt=\"\" src=\"assets/images/icons/icon_kick_m.png\"/>M<img alt=\"\" src=\"assets/images/icons/arrow_3.png\"/><img alt=\"\" src=\"assets/images/icons/icon_kick_m.png\"/>M</p></td>",
    "startup": "<td class=\"frame_startup_frame__Dc2Ph\">14</td>",
    "active": "<td class=\"frame_active_frame__6Sovc\"><p>14-18</p></td>",
    "recovery": "<td class=\"frame_recovery_frame__CznJj\">21</td>",
    "hitAdv": "<td class=\"frame_hit_frame__K7xOz undefined\">-3</td>",
    "guardAdv": "<td class=\"frame_block_frame__SfHiW undefined\">-11</td>",
    "cancel": "<td class=\"frame_cancel__hT_hr\"><span class=\"frame_type_C__nVWNp\">C</span></td>",
    "damage": "<td class=\"frame_damage__HWaQm\">500 </td>",
    "comboMod": "<td class=\"frame_combo_correct__hCDUB\"></td>",
    "driveGain": "<td class=\"frame_drive_gauge_gain_hit___Jg7j\">1000</td>",
    "driveLossGuard": "<td class=\"frame_drive_gauge_lose_dguard__4uQOc\">-2500</td>",
    "driveLossPunish": "<td class=\"frame_drive_gauge_lose_punish__mFrmM\">-4000</td>",
    "saGain": "<td class=\"frame_sa_gauge_gain__oGcqw\">700</td>",
    "attribute": "<td class=\"frame_attribute__1vABD\">Mid</td>",
    "notes": "<td class=\"frame_note__hfwBr\"><p>Adds a floor bounding effect during a mid-air hit</p></td>"
  },
  {
    "section": "Unique Attacks",
    "name": "<td class=\"frame_fixed_m__icTnd frame_skill__tLJuM\"><span class=\"frame_arts__ZU5YI\">Temps Lié</span><p class=\"frame_classic___gpLR\"><img alt=\"\" src=\"assets/images/icons/icon_punch_h.png\"/>H<img alt=\"\" src=\"assets/images/icons/arrow_3.png\"/><img alt=\"\" src=\"assets/images/icons/icon_punch_h.png\"/>H</p></td>",
    "startup": "<td class=\"frame_startup_frame__Dc2Ph\">5</td>",
    "active": "<td class=\"frame_active_frame__6Sovc\"><p>5-6</p></td>",
    "recovery": "<td class=\"frame_recovery_frame__CznJj\">*20</td>",
    "hitAdv": "<td class=\"frame_hit_frame__K7xOz undefined\">3</td>",
    "guardAdv": "<td class=\"frame_block_frame__SfHiW undefined\">-8</td>",
    "cancel": "<td class=\"frame_cancel__hT_hr\"></td>",
    "damage": "<td class=\"frame_damage__HWaQm\">600 </td>",
    "comboMod": "<td class=\"frame_combo_correct__hCDUB\">Combo scaling 20%<br/></td>",
    "driveGain": "<td class=\"frame_drive_gauge_gain_hit___Jg7j\">2000</td>",
    "driveLossGuard": "<td class=\"frame_drive_gauge_lose_dguard__4uQOc\">-5000</td>",
    "driveLossPunish": "<td class=\"frame_drive_gauge_lose_punish__mFrmM\">-7000</td>",
    "saGain": "<td class=\"frame_sa_gauge_gain__oGcqw\">1000</td>",
    "attribute": "<td class=\"frame_attribute__1vABD\">High</td>",
    "notes": "<td class=\"frame_note__hfwBr\"><p>Forces a juggle state when standing heavy punch lands as a Punish Counter.<br/>* 2 frame of recovery added when blocked</p></td>"
  },
  {
    "section": "Unique Attacks",
    "name": "<td class=\"frame_fixed_m__icTnd frame_skill__tLJuM\"><span class=\"frame_arts__ZU5YI\">Allongé</span><p class=\"frame_classic___gpLR\"><img alt=\"\" src=\"assets/images/icons/key-d.png\"/><img alt=\"\" src=\"assets/images/icons/key-plus.png\"/><img alt=\"\" src=\"assets/images/icons/icon_punch_h.png\"/>H<img alt=\"\" src=\"assets/images/icons/arrow_3.png\"/><img alt=\"\" src=\"assets/images/icons/icon_punch_h.png\"/>H</p></td>",
    "startup": "<td class=\"frame_startup_frame__Dc2Ph\">4</td>",
    "active": "<td class=\"frame_active_frame__6Sovc\"><p>4-7</p></td>",
    "recovery": "<td class=\"frame_recovery_frame__CznJj\">26</td>",
    "hitAdv": "<td class=\"frame_hit_frame__K7xOz undefined\">1</td>",
    "guardAdv": "<td class=\"frame_block_frame__SfHiW undefined\">-10</td>",
    "cancel": "<td class=\"frame_cancel__hT_hr\"></td>",
    "damage": "<td class=\"frame_damage__HWaQm\">500 </td>",
    "comboMod": "<td class=\"frame_combo_correct__hCDUB\"></td>",
    "driveGain": "<td class=\"frame_drive_gauge_gain_hit___Jg7j\">4000</td>",
    "driveLossGuard": "<td class=\"frame_drive_gauge_lose_dguard__4uQOc\">-5000</td>",
    "driveLossPunish": "<td class=\"frame_drive_gauge_lose_punish__mFrmM\">-7000</td>",
    "saGain": "<td class=\"frame_sa_gauge_gain__oGcqw\">1000</td>",
    "attribute": "<td class=\"frame_attribute__1vABD\">High</td>",
    "notes": "<td class=\"frame_note__hfwBr\"></td>"
  },
  {
    "section": "Special Moves",
    "name": "<td class=\"frame_fixed_m__icTnd frame_skill__tLJuM\"><span class=\"frame_arts__ZU5YI\">L Manège Doré(Attack changes according to Medal level)</span><p class=\"frame_classic___gpLR\">(When near opponent)<img alt=\"\" src=\"assets/images/icons/key-r.png\"/><img alt=\"\" src=\"assets/images/icons/key-dr.png\"/><img alt=\"\" src=\"assets/images/icons/key-d.png\"/><img alt=\"\" src=\"assets/images/icons/key-dl.png\"/><img alt=\"\" src=\"assets/images/icons/key-l.png\"/> <img alt=\"\" src=\"assets/images/icons/key-plus.png\"/> <img alt=\"\" src=\"assets/images/icons/icon_punch_l.png\"/>L</p></td>",
    "startup": "<td class=\"frame_startup_frame__Dc2Ph\">10</td>",
    "active": "<td class=\"frame_active_frame__6Sovc\"><p>10-11</p></td>",
    "recovery": "<td class=\"frame_recovery_frame__CznJj\">49</td>",
    "hitAdv": "<td class=\"frame_hit_frame__K7xOz\">D</td>",
    "guardAdv": "<td class=\"frame_block_frame__SfHiW\"></td>",
    "cancel": "<td class=\"frame_cancel__hT_hr\"></td>",
    "damage": "<td class=\"frame_damage__HWaQm\">*2000 </td>",
    "comboMod": "<td class=\"frame_combo_correct__hCDUB\"></td>",
    "driveGain": "<td class=\"frame_drive_gauge_gain_hit___Jg7j\">5000</td>",
    "driveLossGuard": "<td class=\"frame_drive_gauge_lose_dguard__4uQOc\">0</td>",
    "driveLossPunish": "<td class=\"frame_drive_gauge_lose_punish__mFrmM\">-10000</td>",
    "saGain": "<td class=\"frame_sa_gauge_gain__oGcqw\">※3000</td>",
    "attribute": "<td class=\"frame_attribute__1vABD\">Throw</td>",
    "notes": "<td class=\"frame_note__hfwBr\"><p>Medal level increases by a single level on hit<br/>*Damage increases the higher the Medal level<br/><br/>Medal Level 1: 2000 (2300)<br/>Medal Level 2: 2300 (2645)<br/>Medal Level 3: 2700 (3105)<br/>Medal Level 4: 3000 (3450)<br/>Medal level 5: 3700 (4255)<br/>Values in parentheses represent damage on Punish Counter<br/><br/>Super Art gauge increase depends on Medal level.<br/>Medal Level 1 - 2: 3000<br/>Medal Level 3 - 4: 4000<br/>Medal Level 5: 5000</p></td>"
  },
  {
    "section": "Special Moves",
    "name": "<td class=\"frame_fixed_m__icTnd frame_skill__tLJuM\"><span class=\"frame_arts__ZU5YI\">M Manège Doré(Attack changes according to Medal level)</span><p class=\"frame_classic___gpLR\">(When near opponent)<img alt=\"\" src=\"assets/images/icons/key-r.png\"/><img alt=\"\" src=\"assets/images/icons/key-dr.png\"/><img alt=\"\" src=\"assets/images/icons/key-d.png\"/><img alt=\"\" src=\"assets/images/icons/key-dl.png\"/><img alt=\"\" src=\"assets/images/icons/key-l.png\"/> <img alt=\"\" src=\"assets/images/icons/key-plus.png\"/> <img alt=\"\" src=\"assets/images/icons/icon_punch_m.png\"/>M</p></td>",
    "startup": "<td class=\"frame_startup_frame__Dc2Ph\">8</td>",
    "active": "<td class=\"frame_active_frame__6Sovc\"><p>8-9</p></td>",
    "recovery": "<td class=\"frame_recovery_frame__CznJj\">51</td>",
    "hitAdv": "<td class=\"frame_hit_frame__K7xOz\">D</td>",
    "guardAdv": "<td class=\"frame_block_frame__SfHiW\"></td>",
    "cancel": "<td class=\"frame_cancel__hT_hr\"></td>",
    "damage": "<td class=\"frame_damage__HWaQm\">*2000 </td>",
    "comboMod": "<td class=\"frame_combo_correct__hCDUB\"></td>",
    "driveGain": "<td class=\"frame_drive_gauge_gain_hit___Jg7j\">5000</td>",
    "driveLossGuard": "<td class=\"frame_drive_gauge_lose_dguard__4uQOc\">0</td>",
    "driveLossPunish": "<td class=\"frame_drive_gauge_lose_punish__mFrmM\">-10000</td>",
    "saGain": "<td class=\"frame_sa_gauge_gain__oGcqw\">※3000</td>",
    "attribute": "<td class=\"frame_attribute__1vABD\">Throw</td>",
    "notes": "<td class=\"frame_note__hfwBr\"><p>Medal level increases by a single level on hit<br/>*Damage increases the higher the Medal level<br/><br/>Medal Level 1: 2000 (2300)<br/>Medal Level 2: 2300 (2645)<br/>Medal Level 3: 2700 (3105)<br/>Medal Level 4: 3000 (3450)<br/>Medal level 5: 3700 (4255)<br/>Values in parentheses represent damage on Punish Counter<br/><br/>Super Art gauge increase depends on Medal level.<br/>Medal Level 1 - 2: 3000<br/>Medal Level 3 - 4: 4000<br/>Medal Level 5: 5000</p></td>"
  },
  {
    "section": "Special Moves",
    "name": "<td class=\"frame_fixed_m__icTnd frame_skill__tLJuM\"><span class=\"frame_arts__ZU5YI\">H Manège Doré(Attack changes according to Medal level)</span><p class=\"frame_classic___gpLR\">(When near opponent)<img alt=\"\" src=\"assets/images/icons/key-r.png\"/><img alt=\"\" src=\"assets/images/icons/key-dr.png\"/><img alt=\"\" src=\"assets/images/icons/key-d.png\"/><img alt=\"\" src=\"assets/images/icons/key-dl.png\"/><img alt=\"\" src=\"assets/images/icons/key-l.png\"/> <img alt=\"\" src=\"assets/images/icons/key-plus.png\"/> <img alt=\"\" src=\"assets/images/icons/icon_punch_h.png\"/>H</p></td>",
    "startup": "<td class=\"frame_startup_frame__Dc2Ph\">5</td>",
    "active": "<td class=\"frame_active_frame__6Sovc\"><p>5-6</p></td>",
    "recovery": "<td class=\"frame_recovery_frame__CznJj\">54</td>",
    "hitAdv": "<td class=\"frame_hit_frame__K7xOz\">D</td>",
    "guardAdv": "<td class=\"frame_block_frame__SfHiW\"></td>",
    "cancel": "<td class=\"frame_cancel__hT_hr\"></td>",
    "damage": "<td class=\"frame_damage__HWaQm\">*2000 </td>",
    "comboMod": "<td class=\"frame_combo_correct__hCDUB\"></td>",
    "driveGain": "<td class=\"frame_drive_gauge_gain_hit___Jg7j\">5000</td>",
    "driveLossGuard": "<td class=\"frame_drive_gauge_lose_dguard__4uQOc\">0</td>",
    "driveLossPunish": "<td class=\"frame_drive_gauge_lose_punish__mFrmM\">-10000</td>",
    "saGain": "<td class=\"frame_sa_gauge_gain__oGcqw\">※3000</td>",
    "attribute": "<td class=\"frame_attribute__1vABD\">Throw</td>",
    "notes": "<td class=\"frame_note__hfwBr\"><p>With Classic Controls<br/>Medal level increases by a single level on hit<br/>*Damage increases the higher the Medal level<br/><br/>Medal Level 1: 2000 (2300)<br/>Medal Level 2: 2300 (2645)<br/>Medal Level 3: 2700 (3105)<br/>Medal Level 4: 3000 (3450)<br/>Medal level 5: 3700 (4255)<br/>Values in parentheses represent damage on Punish Counter<br/><br/>With Modern Controls<br/>Medal level increases by a single level on hit<br/>*Damage increases the higher the Medal level<br/><br/>Medal Level 1: 1600 (2000) / 1840 (2300)<br/>Medal Level 2: 1840 (2300) / 2116 (2645)<br/>Medal Level 3: 2160 (2700) / 2484 (3105)<br/>Medal Level 4: 2400 (3000) / 2760 (3450)<br/>Medal level 5: 2960 (3700) / 3404 (4255)<br/>Values after the backslash represent damage on Punish Counter<br/><br/>Super Art gauge increase depends on Medal level.<br/>Medal Level 1 - 2: 3000<br/>Medal Level 3 - 4: 4000<br/>Medal Level 5: 5000</p></td>"
  },
  {
    "section": "Special Moves",
    "name": "<td class=\"frame_fixed_m__icTnd frame_skill__tLJuM\"><span class=\"frame_arts__ZU5YI\">OD Manège Doré(Attack changes according to Medal level)</span><p class=\"frame_classic___gpLR\">(When near opponent)<img alt=\"\" src=\"assets/images/icons/key-r.png\"/><img alt=\"\" src=\"assets/images/icons/key-dr.png\"/><img alt=\"\" src=\"assets/images/icons/key-d.png\"/><img alt=\"\" src=\"assets/images/icons/key-dl.png\"/><img alt=\"\" src=\"assets/images/icons/key-l.png\"/> <img alt=\"\" src=\"assets/images/icons/key-plus.png\"/> <img alt=\"\" src=\"assets/images/icons/icon_punch.png\"/><img alt=\"\" src=\"assets/images/icons/icon_punch.png\"/></p></td>",
    "startup": "<td class=\"frame_startup_frame__Dc2Ph\">8</td>",
    "active": "<td class=\"frame_active_frame__6Sovc\"><p>8-9</p></td>",
    "recovery": "<td class=\"frame_recovery_frame__CznJj\">51</td>",
    "hitAdv": "<td class=\"frame_hit_frame__K7xOz\">D</td>",
    "guardAdv": "<td class=\"frame_block_frame__SfHiW\"></td>",
    "cancel": "<td class=\"frame_cancel__hT_hr\"></td>",
    "damage": "<td class=\"frame_damage__HWaQm\">*2000 </td>",
    "comboMod": "<td class=\"frame_combo_correct__hCDUB\"></td>",
    "driveGain": "<td class=\"frame_drive_gauge_gain_hit___Jg7j\">0</td>",
    "driveLossGuard": "<td class=\"frame_drive_gauge_lose_dguard__4uQOc\">0</td>",
    "driveLossPunish": "<td class=\"frame_drive_gauge_lose_punish__mFrmM\">-10000</td>",
    "saGain": "<td class=\"frame_sa_gauge_gain__oGcqw\">※3000</td>",
    "attribute": "<td class=\"frame_attribute__1vABD\">Throw</td>",
    "notes": "<td class=\"frame_note__hfwBr\"><p>With Classic Controls<br/>Medal level increases by a single level on hit<br/>*Damage increases the higher the Medal level<br/><br/>Medal Level 1: 2000 (2300)<br/>Medal Level 2: 2300 (2645)<br/>Medal Level 3: 2700 (3105)<br/>Medal Level 4: 3000 (3450)<br/>Medal Level 5: 3700 (4255)<br/>Values in parentheses represent damage on Punish Counter<br/><br/>With Modern Controls<br/>Medal level increases by a single level on hit<br/>*Damage increases the higher the Medal level<br/><br/>Medal Level 1: 1600 (2000) / 1840 (2300)<br/>Medal Level 2: 1840 (2300) / 2116 (2645)<br/>Medal Level 3: 2160 (2700) / 2484 (3105)<br/>Medal Level 4: 2400 (3000) / 2760 (3450)<br/>Medal Level 5: 2960 (3700) / 3404 (4255)<br/>Values after the backslash represent damage on Punish Counter<br/><br/>Super Art gauge increase depends on Medal level.<br/>Medal Level 1 - 2: 3000<br/>Medal Level 3 - 4: 4000<br/>Medal Level 5: 5000</p></td>"
  },
  {
    "section": "Special Moves",
    "name": "<td class=\"frame_fixed_m__icTnd frame_skill__tLJuM\"><span class=\"frame_arts__ZU5YI\">L Rond-point</span><p class=\"frame_classic___gpLR\"><img alt=\"\" src=\"assets/images/icons/key-d.png\"/><img alt=\"\" src=\"assets/images/icons/key-dr.png\"/><img alt=\"\" src=\"assets/images/icons/key-r.png\"/> <img alt=\"\" src=\"assets/images/icons/key-plus.png\"/> <img alt=\"\" src=\"assets/images/icons/icon_kick_l.png\"/>L</p></td>",
    "startup": "<td class=\"frame_startup_frame__Dc2Ph\">9</td>",
    "active": "<td class=\"frame_active_frame__6Sovc\"><input id=\"af_300_82\" type=\"checkbox\"/><label for=\"af_300_82\">9-15</label><div class=\"frame_ex___h3rR\"><div class=\"frame_inner__Qf7xV\">9-11, 14-15</div></div></td>",
    "recovery": "<td class=\"frame_recovery_frame__CznJj\">29</td>",
    "hitAdv": "<td class=\"frame_hit_frame__K7xOz undefined\">3</td>",
    "guardAdv": "<td class=\"frame_block_frame__SfHiW undefined\">-15</td>",
    "cancel": "<td class=\"frame_cancel__hT_hr\"><span class=\"frame_type_SA3__bfGrv\">SA3</span></td>",
    "damage": "<td class=\"frame_damage__HWaQm\">900 </td>",
    "comboMod": "<td class=\"frame_combo_correct__hCDUB\"></td>",
    "driveGain": "<td class=\"frame_drive_gauge_gain_hit___Jg7j\">2000</td>",
    "driveLossGuard": "<td class=\"frame_drive_gauge_lose_dguard__4uQOc\">-4000</td>",
    "driveLossPunish": "<td class=\"frame_drive_gauge_lose_punish__mFrmM\">-4000</td>",
    "saGain": "<td class=\"frame_sa_gauge_gain__oGcqw\">1350</td>",
    "attribute": "<td class=\"frame_attribute__1vABD\">High</td>",
    "notes": "<td class=\"frame_note__hfwBr\"><p>The upper part of Manon's body is invincible against mid-air projectiles and strikes with mid-air hitboxes from frames 5 - 15<br/>Only the second hit can be canceled into a Level 3 Super Art or Critical Art</p></td>"
  },
  {
    "section": "Special Moves",
    "name": "<td class=\"frame_fixed_m__icTnd frame_skill__tLJuM\"><span class=\"frame_arts__ZU5YI\">M Rond-point</span><p class=\"frame_classic___gpLR\"><img alt=\"\" src=\"assets/images/icons/key-d.png\"/><img alt=\"\" src=\"assets/images/icons/key-dr.png\"/><img alt=\"\" src=\"assets/images/icons/key-r.png\"/> <img alt=\"\" src=\"assets/images/icons/key-plus.png\"/> <img alt=\"\" src=\"assets/images/icons/icon_kick_m.png\"/>M</p></td>",
    "startup": "<td class=\"frame_startup_frame__Dc2Ph\">11</td>",
    "active": "<td class=\"frame_active_frame__6Sovc\"><input id=\"af_300_83\" type=\"checkbox\"/><label for=\"af_300_83\">11-19</label><div class=\"frame_ex___h3rR\"><div class=\"frame_inner__Qf7xV\">11-13, 17-19</div></div></td>",
    "recovery": "<td class=\"frame_recovery_frame__CznJj\">27</td>",
    "hitAdv": "<td class=\"frame_hit_frame__K7xOz\">D</td>",
    "guardAdv": "<td class=\"frame_block_frame__SfHiW undefined\">-14</td>",
    "cancel": "<td class=\"frame_cancel__hT_hr\"><span class=\"frame_type_SA3__bfGrv\">SA3</span></td>",
    "damage": "<td class=\"frame_damage__HWaQm\">1000 </td>",
    "comboMod": "<td class=\"frame_combo_correct__hCDUB\"></td>",
    "driveGain": "<td class=\"frame_drive_gauge_gain_hit___Jg7j\">2000</td>",
    "driveLossGuard": "<td class=\"frame_drive_gauge_lose_dguard__4uQOc\">-4000</td>",
    "driveLossPunish": "<td class=\"frame_drive_gauge_lose_punish__mFrmM\">-4000</td>",
    "saGain": "<td class=\"frame_sa_gauge_gain__oGcqw\">1350</td>",
    "attribute": "<td class=\"frame_attribute__1vABD\">High</td>",
    "notes": "<td class=\"frame_note__hfwBr\"><p>The upper part of Manon's body is invincible against mid-air projectiles and strikes with mid-air hitboxes from frames 7 - 19<br/>Only the first hit can be canceled into a Level 3 Super Art or Critical Art</p></td>"
  },
  {
    "section": "Special Moves",
    "name": "<td class=\"frame_fixed_m__icTnd frame_skill__tLJuM\"><span class=\"frame_arts__ZU5YI\">H Rond-point</span><p class=\"frame_classic___gpLR\"><img alt=\"\" src=\"assets/images/icons/key-d.png\"/><img alt=\"\" src=\"assets/images/icons/key-dr.png\"/><img alt=\"\" src=\"assets/images/icons/key-r.png\"/> <img alt=\"\" src=\"assets/images/icons/key-plus.png\"/> <img alt=\"\" src=\"assets/images/icons/icon_kick_h.png\"/>H</p></td>",
    "startup": "<td class=\"frame_startup_frame__Dc2Ph\">14</td>",
    "active": "<td class=\"frame_active_frame__6Sovc\"><input id=\"af_300_84\" type=\"checkbox\"/><label for=\"af_300_84\">14-22</label><div class=\"frame_ex___h3rR\"><div class=\"frame_inner__Qf7xV\">14-16, 20-22</div></div></td>",
    "recovery": "<td class=\"frame_recovery_frame__CznJj\">24</td>",
    "hitAdv": "<td class=\"frame_hit_frame__K7xOz\">D</td>",
    "guardAdv": "<td class=\"frame_block_frame__SfHiW undefined\">-11</td>",
    "cancel": "<td class=\"frame_cancel__hT_hr\"><span class=\"frame_type_SA3__bfGrv\">SA3</span></td>",
    "damage": "<td class=\"frame_damage__HWaQm\">800 </td>",
    "comboMod": "<td class=\"frame_combo_correct__hCDUB\"></td>",
    "driveGain": "<td class=\"frame_drive_gauge_gain_hit___Jg7j\">2000</td>",
    "driveLossGuard": "<td class=\"frame_drive_gauge_lose_dguard__4uQOc\">-4000</td>",
    "driveLossPunish": "<td class=\"frame_drive_gauge_lose_punish__mFrmM\">-4000</td>",
    "saGain": "<td class=\"frame_sa_gauge_gain__oGcqw\">1350</td>",
    "attribute": "<td class=\"frame_attribute__1vABD\">High</td>",
    "notes": "<td class=\"frame_note__hfwBr\"><p>The upper part of Manon's body is invincible against mid-air projectiles and strikes with mid-air hitboxes from frames 9 - 22<br/>Can be canceled into a special move or Super Art from frames 44 - 46 on hit<br/>Only the first hit can be canceled into a Level 3 Super Art or Critical Art</p></td>"
  },
  {
    "section": "Special Moves",
    "name": "<td class=\"frame_fixed_m__icTnd frame_skill__tLJuM\"><span class=\"frame_arts__ZU5YI\">OD Rond-point</span><p class=\"frame_classic___gpLR\"><img alt=\"\" src=\"assets/images/icons/key-d.png\"/><img alt=\"\" src=\"assets/images/icons/key-dr.png\"/><img alt=\"\" src=\"assets/images/icons/key-r.png\"/> <img alt=\"\" src=\"assets/images/icons/key-plus.png\"/> <img alt=\"\" src=\"assets/images/icons/icon_kick.png\"/><img alt=\"\" src=\"assets/images/icons/icon_kick.png\"/></p></td>",
    "startup": "<td class=\"frame_startup_frame__Dc2Ph\">8</td>",
    "active": "<td class=\"frame_active_frame__6Sovc\"><input id=\"af_300_85\" type=\"checkbox\"/><label for=\"af_300_85\">8-16</label><div class=\"frame_ex___h3rR\"><div class=\"frame_inner__Qf7xV\">8-11, 14-16</div></div></td>",
    "recovery": "<td class=\"frame_recovery_frame__CznJj\">30</td>",
    "hitAdv": "<td class=\"frame_hit_frame__K7xOz\">D</td>",
    "guardAdv": "<td class=\"frame_block_frame__SfHiW undefined\">-19</td>",
    "cancel": "<td class=\"frame_cancel__hT_hr\"><span class=\"frame_type_SA2__0_fqx\">SA2</span></td>",
    "damage": "<td class=\"frame_damage__HWaQm\">800 </td>",
    "comboMod": "<td class=\"frame_combo_correct__hCDUB\"></td>",
    "driveGain": "<td class=\"frame_drive_gauge_gain_hit___Jg7j\">0</td>",
    "driveLossGuard": "<td class=\"frame_drive_gauge_lose_dguard__4uQOc\">-4000</td>",
    "driveLossPunish": "<td class=\"frame_drive_gauge_lose_punish__mFrmM\">-4000</td>",
    "saGain": "<td class=\"frame_sa_gauge_gain__oGcqw\">1350</td>",
    "attribute": "<td class=\"frame_attribute__1vABD\">High</td>",
    "notes": "<td class=\"frame_note__hfwBr\"><p>Invincible against mid-air projectiles and strikes with mid-air hitboxes from frames 4 - 16<br/>Can be canceled into a special move or Super Art from frames 41 - 46 on hit</p></td>"
  },
  {
    "section": "Special Moves",
    "name": "<td class=\"frame_fixed_m__icTnd frame_skill__tLJuM\"><span class=\"frame_arts__ZU5YI\">L Dégagé</span><p class=\"frame_classic___gpLR\"><img alt=\"\" src=\"assets/images/icons/key-d.png\"/><img alt=\"\" src=\"assets/images/icons/key-dl.png\"/><img alt=\"\" src=\"assets/images/icons/key-l.png\"/> <img alt=\"\" src=\"assets/images/icons/key-plus.png\"/> <img alt=\"\" src=\"assets/images/icons/icon_kick_l.png\"/>L</p></td>",
    "startup": "<td class=\"frame_startup_frame__Dc2Ph\">16</td>",
    "active": "<td class=\"frame_active_frame__6Sovc\"><input id=\"af_300_86\" type=\"checkbox\"/><label for=\"af_300_86\">16-31</label><div class=\"frame_ex___h3rR\"><div class=\"frame_inner__Qf7xV\">16-17, 28-31</div></div></td>",
    "recovery": "<td class=\"frame_recovery_frame__CznJj\">36</td>",
    "hitAdv": "<td class=\"frame_hit_frame__K7xOz\">D</td>",
    "guardAdv": "<td class=\"frame_block_frame__SfHiW undefined\">-24</td>",
    "cancel": "<td class=\"frame_cancel__hT_hr\"></td>",
    "damage": "<td class=\"frame_damage__HWaQm\">1000 </td>",
    "comboMod": "<td class=\"frame_combo_correct__hCDUB\"></td>",
    "driveGain": "<td class=\"frame_drive_gauge_gain_hit___Jg7j\">1500</td>",
    "driveLossGuard": "<td class=\"frame_drive_gauge_lose_dguard__4uQOc\">-4000</td>",
    "driveLossPunish": "<td class=\"frame_drive_gauge_lose_punish__mFrmM\">-8000</td>",
    "saGain": "<td class=\"frame_sa_gauge_gain__oGcqw\">800</td>",
    "attribute": "<td class=\"frame_attribute__1vABD\">Low</td>",
    "notes": "<td class=\"frame_note__hfwBr\"></td>"
  },
  {
    "section": "Special Moves",
    "name": "<td class=\"frame_fixed_m__icTnd frame_skill__tLJuM\"><span class=\"frame_arts__ZU5YI\">M Dégagé</span><p class=\"frame_classic___gpLR\"><img alt=\"\" src=\"assets/images/icons/key-d.png\"/><img alt=\"\" src=\"assets/images/icons/key-dl.png\"/><img alt=\"\" src=\"assets/images/icons/key-l.png\"/> <img alt=\"\" src=\"assets/images/icons/key-plus.png\"/> <img alt=\"\" src=\"assets/images/icons/icon_kick_m.png\"/>M</p></td>",
    "startup": "<td class=\"frame_startup_frame__Dc2Ph\">16</td>",
    "active": "<td class=\"frame_active_frame__6Sovc\"><input id=\"af_300_87\" type=\"checkbox\"/><label for=\"af_300_87\">16-39</label><div class=\"frame_ex___h3rR\"><div class=\"frame_inner__Qf7xV\">16-19, 34-39</div></div></td>",
    "recovery": "<td class=\"frame_recovery_frame__CznJj\">22</td>",
    "hitAdv": "<td class=\"frame_hit_frame__K7xOz\">D</td>",
    "guardAdv": "<td class=\"frame_block_frame__SfHiW undefined\">-13</td>",
    "cancel": "<td class=\"frame_cancel__hT_hr\"></td>",
    "damage": "<td class=\"frame_damage__HWaQm\">1200 </td>",
    "comboMod": "<td class=\"frame_combo_correct__hCDUB\"></td>",
    "driveGain": "<td class=\"frame_drive_gauge_gain_hit___Jg7j\">2000</td>",
    "driveLossGuard": "<td class=\"frame_drive_gauge_lose_dguard__4uQOc\">-5000</td>",
    "driveLossPunish": "<td class=\"frame_drive_gauge_lose_punish__mFrmM\">-8000</td>",
    "saGain": "<td class=\"frame_sa_gauge_gain__oGcqw\">800</td>",
    "attribute": "<td class=\"frame_attribute__1vABD\">High</td>",
    "notes": "<td class=\"frame_note__hfwBr\"><p>Considered airborne from frames 15 - 39</p></td>"
  },
  {
    "section": "Special Moves",
    "name": "<td class=\"frame_fixed_m__icTnd frame_skill__tLJuM\"><span class=\"frame_arts__ZU5YI\">H  Dégagé</span><p class=\"frame_classic___gpLR\"><img alt=\"\" src=\"assets/images/icons/key-d.png\"/><img alt=\"\" src=\"assets/images/icons/key-dl.png\"/><img alt=\"\" src=\"assets/images/icons/key-l.png\"/> <img alt=\"\" src=\"assets/images/icons/key-plus.png\"/> <img alt=\"\" src=\"assets/images/icons/icon_kick_h.png\"/>H</p></td>",
    "startup": "<td class=\"frame_startup_frame__Dc2Ph\">20</td>",
    "active": "<td class=\"frame_active_frame__6Sovc\"><p>20-22</p></td>",
    "recovery": "<td class=\"frame_recovery_frame__CznJj\">24</td>",
    "hitAdv": "<td class=\"frame_hit_frame__K7xOz undefined\">3</td>",
    "guardAdv": "<td class=\"frame_block_frame__SfHiW undefined\">-9</td>",
    "cancel": "<td class=\"frame_cancel__hT_hr\"></td>",
    "damage": "<td class=\"frame_damage__HWaQm\">1000 </td>",
    "comboMod": "<td class=\"frame_combo_correct__hCDUB\"></td>",
    "driveGain": "<td class=\"frame_drive_gauge_gain_hit___Jg7j\">3000</td>",
    "driveLossGuard": "<td class=\"frame_drive_gauge_lose_dguard__4uQOc\">-4000</td>",
    "driveLossPunish": "<td class=\"frame_drive_gauge_lose_punish__mFrmM\">-5000</td>",
    "saGain": "<td class=\"frame_sa_gauge_gain__oGcqw\">800</td>",
    "attribute": "<td class=\"frame_attribute__1vABD\">Mid</td>",
    "notes": "<td class=\"frame_note__hfwBr\"><p>Low attack invincibility from frames 9 - 19</p></td>"
  },
  {
    "section": "Special Moves",
    "name": "<td class=\"frame_fixed_m__icTnd frame_skill__tLJuM\"><span class=\"frame_arts__ZU5YI\">OD Dégagé</span><p class=\"frame_classic___gpLR\"><img alt=\"\" src=\"assets/images/icons/key-d.png\"/><img alt=\"\" src=\"assets/images/icons/key-dl.png\"/><img alt=\"\" src=\"assets/images/icons/key-l.png\"/> <img alt=\"\" src=\"assets/images/icons/key-plus.png\"/> <img alt=\"\" src=\"assets/images/icons/icon_kick.png\"/><img alt=\"\" src=\"assets/images/icons/icon_kick.png\"/></p></td>",
    "startup": "<td class=\"frame_startup_frame__Dc2Ph\">22</td>",
    "active": "<td class=\"frame_active_frame__6Sovc\"><p>22-24</p></td>",
    "recovery": "<td class=\"frame_recovery_frame__CznJj\">22</td>",
    "hitAdv": "<td class=\"frame_hit_frame__K7xOz undefined\">6</td>",
    "guardAdv": "<td class=\"frame_block_frame__SfHiW undefined\">-3</td>",
    "cancel": "<td class=\"frame_cancel__hT_hr\"></td>",
    "damage": "<td class=\"frame_damage__HWaQm\">800 </td>",
    "comboMod": "<td class=\"frame_combo_correct__hCDUB\">Starter scaling 20%<br/></td>",
    "driveGain": "<td class=\"frame_drive_gauge_gain_hit___Jg7j\">0</td>",
    "driveLossGuard": "<td class=\"frame_drive_gauge_lose_dguard__4uQOc\">-4000</td>",
    "driveLossPunish": "<td class=\"frame_drive_gauge_lose_punish__mFrmM\">-5000</td>",
    "saGain": "<td class=\"frame_sa_gauge_gain__oGcqw\">800</td>",
    "attribute": "<td class=\"frame_attribute__1vABD\">Mid</td>",
    "notes": "<td class=\"frame_note__hfwBr\"><p>Low attack invincibility from frames 11 - 12, as well as throw invincibility<br/>Considered airborne from frames 9 - 21</p></td>"
  },
  {
    "section": "Special Moves",
    "name": "<td class=\"frame_fixed_m__icTnd frame_skill__tLJuM\"><span class=\"frame_arts__ZU5YI\">L Renversé(Attack changes according to Medal level)</span><p class=\"frame_classic___gpLR\"><img alt=\"\" src=\"assets/images/icons/key-d.png\"/><img alt=\"\" src=\"assets/images/icons/key-dr.png\"/><img alt=\"\" src=\"assets/images/icons/key-r.png\"/> <img alt=\"\" src=\"assets/images/icons/key-plus.png\"/> <img alt=\"\" src=\"assets/images/icons/icon_punch_l.png\"/>L</p></td>",
    "startup": "<td class=\"frame_startup_frame__Dc2Ph\">22</td>",
    "active": "<td class=\"frame_active_frame__6Sovc\"><p>22-23</p></td>",
    "recovery": "<td class=\"frame_recovery_frame__CznJj\">37</td>",
    "hitAdv": "<td class=\"frame_hit_frame__K7xOz\">D</td>",
    "guardAdv": "<td class=\"frame_block_frame__SfHiW undefined\">-23</td>",
    "cancel": "<td class=\"frame_cancel__hT_hr\"><span class=\"frame_type_SA3__bfGrv\">SA3</span></td>",
    "damage": "<td class=\"frame_damage__HWaQm\">*1350 </td>",
    "comboMod": "<td class=\"frame_combo_correct__hCDUB\"></td>",
    "driveGain": "<td class=\"frame_drive_gauge_gain_hit___Jg7j\">2000</td>",
    "driveLossGuard": "<td class=\"frame_drive_gauge_lose_dguard__4uQOc\">-2000</td>",
    "driveLossPunish": "<td class=\"frame_drive_gauge_lose_punish__mFrmM\">-8000</td>",
    "saGain": "<td class=\"frame_sa_gauge_gain__oGcqw\">※2150</td>",
    "attribute": "<td class=\"frame_attribute__1vABD\">High</td>",
    "notes": "<td class=\"frame_note__hfwBr\"><p>With Classic Controls<br/>Projectile invincibility from frames 3 - 21<br/>Transition into feint by holding the button (total 31 frames)<br/>Medal level increases by a single level on hit<br/>*Damage increases the higher the Medal level<br/><br/>Medal Level 1: 1350 (1360)<br/>Medal Level 2: 1500 (1510)<br/>Medal Level 3: 1650 (1660)<br/>Medal Level 4: 1800 (1810)<br/>Medal Level 5: 1950 (1960)<br/>Values in parentheses represent damage on Punish Counter<br/><br/>With Modern Controls<br/>Medal level increases by a single level on hit<br/>*Damage increases the higher the Medal level<br/><br/>Medal Level 1: 1080 / 1088<br/>Medal Level 2: 1200 / 1208<br/>Medal Level 3: 1320 / 1328<br/>Medal Level 4: 1440 / 1448<br/>Medal Level 5: 1560 / 1568<br/>Values after the backslash represent damage on Punish Counter<br/><br/>Super Art gauge increase depends on Medal level.<br/>Medal Level 1 - 2: 2150<br/>Medal Level 3 - 4: 3150<br/>Medal Level 5: 4150</p></td>"
  },
  {
    "section": "Special Moves",
    "name": "<td class=\"frame_fixed_m__icTnd frame_skill__tLJuM\"><span class=\"frame_arts__ZU5YI\">M Renversé(Attack changes according to Medal level)</span><p class=\"frame_classic___gpLR\"><img alt=\"\" src=\"assets/images/icons/key-d.png\"/><img alt=\"\" src=\"assets/images/icons/key-dr.png\"/><img alt=\"\" src=\"assets/images/icons/key-r.png\"/> <img alt=\"\" src=\"assets/images/icons/key-plus.png\"/> <img alt=\"\" src=\"assets/images/icons/icon_punch_m.png\"/>M</p></td>",
    "startup": "<td class=\"frame_startup_frame__Dc2Ph\">25</td>",
    "active": "<td class=\"frame_active_frame__6Sovc\"><p>25-26</p></td>",
    "recovery": "<td class=\"frame_recovery_frame__CznJj\">34</td>",
    "hitAdv": "<td class=\"frame_hit_frame__K7xOz\">D</td>",
    "guardAdv": "<td class=\"frame_block_frame__SfHiW undefined\">-20</td>",
    "cancel": "<td class=\"frame_cancel__hT_hr\"><span class=\"frame_type_SA3__bfGrv\">SA3</span></td>",
    "damage": "<td class=\"frame_damage__HWaQm\">*1400 </td>",
    "comboMod": "<td class=\"frame_combo_correct__hCDUB\"></td>",
    "driveGain": "<td class=\"frame_drive_gauge_gain_hit___Jg7j\">2000</td>",
    "driveLossGuard": "<td class=\"frame_drive_gauge_lose_dguard__4uQOc\">-2000</td>",
    "driveLossPunish": "<td class=\"frame_drive_gauge_lose_punish__mFrmM\">-8000</td>",
    "saGain": "<td class=\"frame_sa_gauge_gain__oGcqw\">※2150</td>",
    "attribute": "<td class=\"frame_attribute__1vABD\">High</td>",
    "notes": "<td class=\"frame_note__hfwBr\"><p>Projectile invincibility from frames 3 - 24<br/>Transition into feint by holding the button (total 32 frames)<br/>Medal level increases by a single level on hit<br/>*Damage increases the higher the Medal level<br/><br/>Medal Level 1: 1400 (1420)<br/>Medal Level 2: 1550 (1570)<br/>Medal Level 3: 1700 (1720)<br/>Medal Level 4: 1850 (1870)<br/>Medal Level 5: 2000 (2020)<br/>Values in parentheses represent damage on Punish Counter<br/><br/>Super Art gauge increase depends on Medal level.<br/>Medal Level 1 - 2: 2150<br/>Medal Level 3 - 4: 3150<br/>Medal Level 5: 4150</p></td>"
  },
  {
    "section": "Special Moves",
    "name": "<td class=\"frame_fixed_m__icTnd frame_skill__tLJuM\"><span class=\"frame_arts__ZU5YI\">H Renversé(Attack changes according to Medal level)</span><p class=\"frame_classic___gpLR\"><img alt=\"\" src=\"assets/images/icons/key-d.png\"/><img alt=\"\" src=\"assets/images/icons/key-dr.png\"/><img alt=\"\" src=\"assets/images/icons/key-r.png\"/> <img alt=\"\" src=\"assets/images/icons/key-plus.png\"/> <img alt=\"\" src=\"assets/images/icons/icon_punch_h.png\"/>H</p></td>",
    "startup": "<td class=\"frame_startup_frame__Dc2Ph\">29</td>",
    "active": "<td class=\"frame_active_frame__6Sovc\"><p>29-30</p></td>",
    "recovery": "<td class=\"frame_recovery_frame__CznJj\">30</td>",
    "hitAdv": "<td class=\"frame_hit_frame__K7xOz\">D</td>",
    "guardAdv": "<td class=\"frame_block_frame__SfHiW undefined\">-16</td>",
    "cancel": "<td class=\"frame_cancel__hT_hr\"><span class=\"frame_type_SA3__bfGrv\">SA3</span></td>",
    "damage": "<td class=\"frame_damage__HWaQm\">*1500 </td>",
    "comboMod": "<td class=\"frame_combo_correct__hCDUB\"></td>",
    "driveGain": "<td class=\"frame_drive_gauge_gain_hit___Jg7j\">2000</td>",
    "driveLossGuard": "<td class=\"frame_drive_gauge_lose_dguard__4uQOc\">-2000</td>",
    "driveLossPunish": "<td class=\"frame_drive_gauge_lose_punish__mFrmM\">-8000</td>",
    "saGain": "<td class=\"frame_sa_gauge_gain__oGcqw\">※2150</td>",
    "attribute": "<td class=\"frame_attribute__1vABD\">High</td>",
    "notes": "<td class=\"frame_note__hfwBr\"><p>Projectile invincibility from frames 3 - 28<br/>Transition into feint by holding the button (total 33 frames)<br/>Medal level increases by a single level on hit<br/>*Damage increases the higher the Medal level<br/><br/>Medal Level 1: 1500 (1540)<br/>Medal Level 2: 1650 (1690)<br/>Medal Level 3: 1800 (1840)<br/>Medal Level 4: 1950 (1990)<br/>Medal Level 5: 2100 (2140)<br/>Values in parentheses represent damage on Punish Counter<br/><br/>Super Art gauge increase depends on Medal level.<br/>Medal Level 1 - 2: 2150<br/>Medal Level 3 - 4: 3150<br/>Medal Level 5: 4150</p></td>"
  },
  {
    "section": "Special Moves",
    "name": "<td class=\"frame_fixed_m__icTnd frame_skill__tLJuM\"><span class=\"frame_arts__ZU5YI\">OD Renversé(Attack changes according to Medal level)</span><p class=\"frame_classic___gpLR\"><img alt=\"\" src=\"assets/images/icons/key-d.png\"/><img alt=\"\" src=\"assets/images/icons/key-dr.png\"/><img alt=\"\" src=\"assets/images/icons/key-r.png\"/> <img alt=\"\" src=\"assets/images/icons/key-plus.png\"/> <img alt=\"\" src=\"assets/images/icons/icon_punch.png\"/><img alt=\"\" src=\"assets/images/icons/icon_punch.png\"/></p></td>",
    "startup": "<td class=\"frame_startup_frame__Dc2Ph\">25</td>",
    "active": "<td class=\"frame_active_frame__6Sovc\"><p>25-26</p></td>",
    "recovery": "<td class=\"frame_recovery_frame__CznJj\">34</td>",
    "hitAdv": "<td class=\"frame_hit_frame__K7xOz\">D</td>",
    "guardAdv": "<td class=\"frame_block_frame__SfHiW undefined\">-20</td>",
    "cancel": "<td class=\"frame_cancel__hT_hr\"></td>",
    "damage": "<td class=\"frame_damage__HWaQm\">*1500 </td>",
    "comboMod": "<td class=\"frame_combo_correct__hCDUB\"></td>",
    "driveGain": "<td class=\"frame_drive_gauge_gain_hit___Jg7j\">0</td>",
    "driveLossGuard": "<td class=\"frame_drive_gauge_lose_dguard__4uQOc\">-2000</td>",
    "driveLossPunish": "<td class=\"frame_drive_gauge_lose_punish__mFrmM\">-8000</td>",
    "saGain": "<td class=\"frame_sa_gauge_gain__oGcqw\">※2150</td>",
    "attribute": "<td class=\"frame_attribute__1vABD\">High</td>",
    "notes": "<td class=\"frame_note__hfwBr\"><p>With Classic Controls<br/>Invincible against strikes from the knee and up from frames 3 - 26<br/>Invincible against projectiles from frames 3 - 26<br/>Transition into feint by holding the button (total 32 frames)<br/>Medal level increases by a single level on hit<br/>*Damage increases the higher the Medal level<br/><br/>Medal Level 1: 1500 (1540)<br/>Medal Level 2: 1650 (1690)<br/>Medal Level 3: 1800 (1840)<br/>Medal Level 4: 1950 (1990)<br/>Medal Level 5: 2100 (2140)<br/>Values in parentheses represent damage on Punish Counter<br/><br/>With Modern Controls<br/>Medal level increases by a single level on hit<br/>*Damage increases the higher the Medal level<br/><br/>Medal Level 1: 1200 / 1232<br/>Medal Level 2: 1320 / 1352<br/>Medal Level 3: 1440 / 1472<br/>Medal Level 4: 1560 / 1592<br/>Medal Level 5: 1680 / 1712<br/>Values after the backslash represent damage on Punish Counter<br/><br/>Super Art gauge increase depends on Medal level.<br/>Medal Level 1 - 2: 2150<br/>Medal Level 3 - 4: 3150<br/>Medal Level 5: 4150</p></td>"
  },
  {
    "section": "Special Moves",
    "name": "<td class=\"frame_fixed_m__icTnd frame_skill__tLJuM\"><span class=\"frame_arts__ZU5YI\">Grand Fouetté</span><p class=\"frame_classic___gpLR\">(During Renversé)<img alt=\"\" src=\"assets/images/icons/icon_kick.png\"/></p></td>",
    "startup": "<td class=\"frame_startup_frame__Dc2Ph\">11</td>",
    "active": "<td class=\"frame_active_frame__6Sovc\"><p>11-16</p></td>",
    "recovery": "<td class=\"frame_recovery_frame__CznJj\">22</td>",
    "hitAdv": "<td class=\"frame_hit_frame__K7xOz\">D</td>",
    "guardAdv": "<td class=\"frame_block_frame__SfHiW undefined\">-5</td>",
    "cancel": "<td class=\"frame_cancel__hT_hr\"><span class=\"frame_type_SA3__bfGrv\">SA3</span></td>",
    "damage": "<td class=\"frame_damage__HWaQm\">800 </td>",
    "comboMod": "<td class=\"frame_combo_correct__hCDUB\">Immediate scaling 10%<br/></td>",
    "driveGain": "<td class=\"frame_drive_gauge_gain_hit___Jg7j\">2500</td>",
    "driveLossGuard": "<td class=\"frame_drive_gauge_lose_dguard__4uQOc\">-5000</td>",
    "driveLossPunish": "<td class=\"frame_drive_gauge_lose_punish__mFrmM\">-10000</td>",
    "saGain": "<td class=\"frame_sa_gauge_gain__oGcqw\">1150</td>",
    "attribute": "<td class=\"frame_attribute__1vABD\">High</td>",
    "notes": "<td class=\"frame_note__hfwBr\"></td>"
  },
  {
    "section": "Special Moves",
    "name": "<td class=\"frame_fixed_m__icTnd frame_skill__tLJuM\"><span class=\"frame_arts__ZU5YI\">OD Grand Fouetté</span><p class=\"frame_classic___gpLR\">(During OD Renversé)<img alt=\"\" src=\"assets/images/icons/icon_kick.png\"/></p></td>",
    "startup": "<td class=\"frame_startup_frame__Dc2Ph\">10</td>",
    "active": "<td class=\"frame_active_frame__6Sovc\"><p>10-15</p></td>",
    "recovery": "<td class=\"frame_recovery_frame__CznJj\">22</td>",
    "hitAdv": "<td class=\"frame_hit_frame__K7xOz\">D</td>",
    "guardAdv": "<td class=\"frame_block_frame__SfHiW undefined\">-12</td>",
    "cancel": "<td class=\"frame_cancel__hT_hr\"><span class=\"frame_type_SA2__0_fqx\">SA2</span></td>",
    "damage": "<td class=\"frame_damage__HWaQm\">800 </td>",
    "comboMod": "<td class=\"frame_combo_correct__hCDUB\">Immediate scaling 10%<br/></td>",
    "driveGain": "<td class=\"frame_drive_gauge_gain_hit___Jg7j\">0</td>",
    "driveLossGuard": "<td class=\"frame_drive_gauge_lose_dguard__4uQOc\">-4000</td>",
    "driveLossPunish": "<td class=\"frame_drive_gauge_lose_punish__mFrmM\">-5000</td>",
    "saGain": "<td class=\"frame_sa_gauge_gain__oGcqw\">1150</td>",
    "attribute": "<td class=\"frame_attribute__1vABD\">High</td>",
    "notes": "<td class=\"frame_note__hfwBr\"></td>"
  },
  {
    "section": "Super Arts",
    "name": "<td class=\"frame_fixed_m__icTnd frame_skill__tLJuM\"><span class=\"frame_arts__ZU5YI\">SA1 Arabesque</span><p class=\"frame_classic___gpLR\"><img alt=\"\" src=\"assets/images/icons/key-d.png\"/><img alt=\"\" src=\"assets/images/icons/key-dr.png\"/><img alt=\"\" src=\"assets/images/icons/key-r.png\"/><img alt=\"\" src=\"assets/images/icons/key-d.png\"/><img alt=\"\" src=\"assets/images/icons/key-dr.png\"/><img alt=\"\" src=\"assets/images/icons/key-r.png\"/> <img alt=\"\" src=\"assets/images/icons/key-plus.png\"/> <img alt=\"\" src=\"assets/images/icons/icon_kick.png\"/></p></td>",
    "startup": "<td class=\"frame_startup_frame__Dc2Ph\">10</td>",
    "active": "<td class=\"frame_active_frame__6Sovc\"><p>10-13</p></td>",
    "recovery": "<td class=\"frame_recovery_frame__CznJj\">65</td>",
    "hitAdv": "<td class=\"frame_hit_frame__K7xOz\">D</td>",
    "guardAdv": "<td class=\"frame_block_frame__SfHiW undefined\">-49</td>",
    "cancel": "<td class=\"frame_cancel__hT_hr\"></td>",
    "damage": "<td class=\"frame_damage__HWaQm\">2000 </td>",
    "comboMod": "<td class=\"frame_combo_correct__hCDUB\"></td>",
    "driveGain": "<td class=\"frame_drive_gauge_gain_hit___Jg7j\">0</td>",
    "driveLossGuard": "<td class=\"frame_drive_gauge_lose_dguard__4uQOc\">-2500</td>",
    "driveLossPunish": "<td class=\"frame_drive_gauge_lose_punish__mFrmM\">0</td>",
    "saGain": "<td class=\"frame_sa_gauge_gain__oGcqw\">0</td>",
    "attribute": "<td class=\"frame_attribute__1vABD\">Low</td>",
    "notes": "<td class=\"frame_note__hfwBr\"><p>Invincible against strikes and throws from frames 1 - 13<br/>Minimum guaranteed damage is 30%<br/>Values do not change on counter or Punish Counter</p></td>"
  },
  {
    "section": "Super Arts",
    "name": "<td class=\"frame_fixed_m__icTnd frame_skill__tLJuM\"><span class=\"frame_arts__ZU5YI\">SA2 Étoile</span><p class=\"frame_classic___gpLR\"><img alt=\"\" src=\"assets/images/icons/key-d.png\"/><img alt=\"\" src=\"assets/images/icons/key-dl.png\"/><img alt=\"\" src=\"assets/images/icons/key-l.png\"/><img alt=\"\" src=\"assets/images/icons/key-d.png\"/><img alt=\"\" src=\"assets/images/icons/key-dl.png\"/><img alt=\"\" src=\"assets/images/icons/key-l.png\"/> <img alt=\"\" src=\"assets/images/icons/key-plus.png\"/> <img alt=\"\" src=\"assets/images/icons/icon_kick.png\"/></p></td>",
    "startup": "<td class=\"frame_startup_frame__Dc2Ph\">7</td>",
    "active": "<td class=\"frame_active_frame__6Sovc\"><input id=\"af_400_97\" type=\"checkbox\"/><label for=\"af_400_97\">7-80</label><div class=\"frame_ex___h3rR\"><div class=\"frame_inner__Qf7xV\">7-9,21-26,72-80</div></div></td>",
    "recovery": "<td class=\"frame_recovery_frame__CznJj\">38+34 frame(s) after landing</td>",
    "hitAdv": "<td class=\"frame_hit_frame__K7xOz\">D</td>",
    "guardAdv": "<td class=\"frame_block_frame__SfHiW undefined\">-61</td>",
    "cancel": "<td class=\"frame_cancel__hT_hr\"></td>",
    "damage": "<td class=\"frame_damage__HWaQm\">2800 </td>",
    "comboMod": "<td class=\"frame_combo_correct__hCDUB\"></td>",
    "driveGain": "<td class=\"frame_drive_gauge_gain_hit___Jg7j\">0</td>",
    "driveLossGuard": "<td class=\"frame_drive_gauge_lose_dguard__4uQOc\">-1000</td>",
    "driveLossPunish": "<td class=\"frame_drive_gauge_lose_punish__mFrmM\">0</td>",
    "saGain": "<td class=\"frame_sa_gauge_gain__oGcqw\">0</td>",
    "attribute": "<td class=\"frame_attribute__1vABD\">High</td>",
    "notes": "<td class=\"frame_note__hfwBr\"><p>Completely invincible from frames 1 - 9<br/>Considered airborne from frames 21 - 36 and 68 - 118<br/>Minimum guaranteed damage is 40%<br/>Values do not change on counter or Punish Counter</p></td>"
  },
  {
    "section": "Super Arts",
    "name": "<td class=\"frame_fixed_m__icTnd frame_skill__tLJuM\"><span class=\"frame_arts__ZU5YI\">SA3 Pas de Deux</span><p class=\"frame_classic___gpLR\">(When near opponent)<img alt=\"\" src=\"assets/images/icons/key-d.png\"/><img alt=\"\" src=\"assets/images/icons/key-dr.png\"/><img alt=\"\" src=\"assets/images/icons/key-r.png\"/><img alt=\"\" src=\"assets/images/icons/key-d.png\"/><img alt=\"\" src=\"assets/images/icons/key-dr.png\"/><img alt=\"\" src=\"assets/images/icons/key-r.png\"/> <img alt=\"\" src=\"assets/images/icons/key-plus.png\"/> <img alt=\"\" src=\"assets/images/icons/icon_punch.png\"/></p></td>",
    "startup": "<td class=\"frame_startup_frame__Dc2Ph\">7</td>",
    "active": "<td class=\"frame_active_frame__6Sovc\"><p>7-8</p></td>",
    "recovery": "<td class=\"frame_recovery_frame__CznJj\">72</td>",
    "hitAdv": "<td class=\"frame_hit_frame__K7xOz\">D</td>",
    "guardAdv": "<td class=\"frame_block_frame__SfHiW\"></td>",
    "cancel": "<td class=\"frame_cancel__hT_hr\"></td>",
    "damage": "<td class=\"frame_damage__HWaQm\">4000 </td>",
    "comboMod": "<td class=\"frame_combo_correct__hCDUB\">*Immediate scaling 5％<br/></td>",
    "driveGain": "<td class=\"frame_drive_gauge_gain_hit___Jg7j\">0</td>",
    "driveLossGuard": "<td class=\"frame_drive_gauge_lose_dguard__4uQOc\">0</td>",
    "driveLossPunish": "<td class=\"frame_drive_gauge_lose_punish__mFrmM\">0</td>",
    "saGain": "<td class=\"frame_sa_gauge_gain__oGcqw\">0</td>",
    "attribute": "<td class=\"frame_attribute__1vABD\">Throw</td>",
    "notes": "<td class=\"frame_note__hfwBr\"><p>Completely invincible from frames 1 - 8<br/>Minimum guaranteed damage is 50%<br/>Values do not change on counter or Punish Counter<br/>*Adds immediate scaling of 15% when canceling from standing Heavy Punch and Ront-point<br/>*Damage increases the higher the Medal level<br/>Medal Level 1: 4000<br/>Medal Level 2: 4100<br/>Medal Level 3: 4200<br/>Medal Level 4: 4400<br/>Medal Level 5: 4600</p></td>"
  },
  {
    "section": "Super Arts",
    "name": "<td class=\"frame_fixed_m__icTnd frame_skill__tLJuM\"><span class=\"frame_arts__ZU5YI\">CA Pas de Deux</span><p class=\"frame_classic___gpLR\">(When near opponent)(when under 25% vitality)<img alt=\"\" src=\"assets/images/icons/key-d.png\"/><img alt=\"\" src=\"assets/images/icons/key-dr.png\"/><img alt=\"\" src=\"assets/images/icons/key-r.png\"/><img alt=\"\" src=\"assets/images/icons/key-d.png\"/><img alt=\"\" src=\"assets/images/icons/key-dr.png\"/><img alt=\"\" src=\"assets/images/icons/key-r.png\"/> <img alt=\"\" src=\"assets/images/icons/key-plus.png\"/> <img alt=\"\" src=\"assets/images/icons/icon_punch.png\"/></p></td>",
    "startup": "<td class=\"frame_startup_frame__Dc2Ph\">7</td>",
    "active": "<td class=\"frame_active_frame__6Sovc\"><p>7-8</p></td>",
    "recovery": "<td class=\"frame_recovery_frame__CznJj\">72</td>",
    "hitAdv": "<td class=\"frame_hit_frame__K7xOz\">D</td>",
    "guardAdv": "<td class=\"frame_block_frame__SfHiW\"></td>",
    "cancel": "<td class=\"frame_cancel__hT_hr\"></td>",
    "damage": "<td class=\"frame_damage__HWaQm\">4500 </td>",
    "comboMod": "<td class=\"frame_combo_correct__hCDUB\">*Immediate scaling 5％<br/></td>",
    "driveGain": "<td class=\"frame_drive_gauge_gain_hit___Jg7j\">0</td>",
    "driveLossGuard": "<td class=\"frame_drive_gauge_lose_dguard__4uQOc\">0</td>",
    "driveLossPunish": "<td class=\"frame_drive_gauge_lose_punish__mFrmM\">0</td>",
    "saGain": "<td class=\"frame_sa_gauge_gain__oGcqw\">0</td>",
    "attribute": "<td class=\"frame_attribute__1vABD\">Throw</td>",
    "notes": "<td class=\"frame_note__hfwBr\"><p>Completely invincible from frames 1 - 8<br/>Minimum guaranteed damage is 50%<br/>Values do not change on counter or Punish Counter<br/>*Adds immediate scaling of 15% when canceling from standing Heavy Punch and Ront-point<br/>*Damage increases the higher the Medal level<br/>Medal Level 1: 4500<br/>Medal Level 2: 4600<br/>Medal Level 3: 4700<br/>Medal Level 4: 4900<br/>Medal Level 5: 5100</p></td>"
  },
  {
    "section": "Throws",
    "name": "<td class=\"frame_fixed_m__icTnd frame_skill__tLJuM\"><span class=\"frame_arts__ZU5YI\">Ouchi Gari</span><p class=\"frame_classic___gpLR\">(When near opponent)<img alt=\"\" src=\"assets/images/icons/key-nutral.png\"/> <img alt=\"\" src=\"assets/images/icons/key-or.png\"/> <img alt=\"\" src=\"assets/images/icons/key-r.png\"/> <img alt=\"\" src=\"assets/images/icons/key-plus.png\"/> <img alt=\"\" src=\"assets/images/icons/icon_punch_l.png\"/>L<img alt=\"\" src=\"assets/images/icons/icon_kick_l.png\"/>L</p></td>",
    "startup": "<td class=\"frame_startup_frame__Dc2Ph\">5</td>",
    "active": "<td class=\"frame_active_frame__6Sovc\"><p>5-7</p></td>",
    "recovery": "<td class=\"frame_recovery_frame__CznJj\">23</td>",
    "hitAdv": "<td class=\"frame_hit_frame__K7xOz\">D</td>",
    "guardAdv": "<td class=\"frame_block_frame__SfHiW\"></td>",
    "cancel": "<td class=\"frame_cancel__hT_hr\"></td>",
    "damage": "<td class=\"frame_damage__HWaQm\">1200 </td>",
    "comboMod": "<td class=\"frame_combo_correct__hCDUB\">Immediate scaling 20％<br/></td>",
    "driveGain": "<td class=\"frame_drive_gauge_gain_hit___Jg7j\">2000</td>",
    "driveLossGuard": "<td class=\"frame_drive_gauge_lose_dguard__4uQOc\">0</td>",
    "driveLossPunish": "<td class=\"frame_drive_gauge_lose_punish__mFrmM\">-10000</td>",
    "saGain": "<td class=\"frame_sa_gauge_gain__oGcqw\">2000</td>",
    "attribute": "<td class=\"frame_attribute__1vABD\"></td>",
    "notes": "<td class=\"frame_note__hfwBr\"><p>Properties change to the following when the attack lands as a Punish Counter:<br/>- Deals 2040 damage<br/>- Super Art gauge increases by 4000<br/>- Forces a hard knockdown</p></td>"
  },
  {
    "section": "Throws",
    "name": "<td class=\"frame_fixed_m__icTnd frame_skill__tLJuM\"><span class=\"frame_arts__ZU5YI\">Uchi Mata</span><p class=\"frame_classic___gpLR\">(When near opponent)<img alt=\"\" src=\"assets/images/icons/key-l.png\"/> <img alt=\"\" src=\"assets/images/icons/key-plus.png\"/> <img alt=\"\" src=\"assets/images/icons/icon_punch_l.png\"/>L<img alt=\"\" src=\"assets/images/icons/icon_kick_l.png\"/>L</p></td>",
    "startup": "<td class=\"frame_startup_frame__Dc2Ph\">5</td>",
    "active": "<td class=\"frame_active_frame__6Sovc\"><p>5-7</p></td>",
    "recovery": "<td class=\"frame_recovery_frame__CznJj\">23</td>",
    "hitAdv": "<td class=\"frame_hit_frame__K7xOz\">D</td>",
    "guardAdv": "<td class=\"frame_block_frame__SfHiW\"></td>",
    "cancel": "<td class=\"frame_cancel__hT_hr\"></td>",
    "damage": "<td class=\"frame_damage__HWaQm\">1200 </td>",
    "comboMod": "<td class=\"frame_combo_correct__hCDUB\">Immediate scaling 20％<br/></td>",
    "driveGain": "<td class=\"frame_drive_gauge_gain_hit___Jg7j\">2000</td>",
    "driveLossGuard": "<td class=\"frame_drive_gauge_lose_dguard__4uQOc\">0</td>",
    "driveLossPunish": "<td class=\"frame_drive_gauge_lose_punish__mFrmM\">-10000</td>",
    "saGain": "<td class=\"frame_sa_gauge_gain__oGcqw\">2000</td>",
    "attribute": "<td class=\"frame_attribute__1vABD\"></td>",
    "notes": "<td class=\"frame_note__hfwBr\"><p>Properties change to the following when the attack lands as a Punish Counter:<br/>- Deals 2040 damage<br/>- Super Art gauge increases by 4000<br/>- Forces a hard knockdown</p></td>"
  },
  {
    "section": "Common Moves",
    "name": "<td class=\"frame_fixed_m__icTnd frame_skill__tLJuM\"><span class=\"frame_arts__ZU5YI\">Forward Dash</span><p class=\"frame_classic___gpLR\"><img alt=\"\" src=\"assets/images/icons/key-r.png\"/><img alt=\"\" src=\"assets/images/icons/key-r.png\"/></p></td>",
    "startup": "<td class=\"frame_startup_frame__Dc2Ph\"></td>",
    "active": "<td class=\"frame_active_frame__6Sovc\"></td>",
    "recovery": "<td class=\"frame_recovery_frame__CznJj\">21 total frames</td>",
    "hitAdv": "<td class=\"frame_hit_frame__K7xOz\"></td>",
    "guardAdv": "<td class=\"frame_block_frame__SfHiW\"></td>",
    "cancel": "<td class=\"frame_cancel__hT_hr\"></td>",
    "damage": "<td class=\"frame_damage__HWaQm\">0 </td>",
    "comboMod": "<td class=\"frame_combo_correct__hCDUB\"></td>",
    "driveGain": "<td class=\"frame_drive_gauge_gain_hit___Jg7j\">0</td>",
    "driveLossGuard": "<td class=\"frame_drive_gauge_lose_dguard__4uQOc\">0</td>",
    "driveLossPunish": "<td class=\"frame_drive_gauge_lose_punish__mFrmM\">0</td>",
    "saGain": "<td class=\"frame_sa_gauge_gain__oGcqw\">0</td>",
    "attribute": "<td class=\"frame_attribute__1vABD\"></td>",
    "notes": "<td class=\"frame_note__hfwBr\"></td>"
  },
  {
    "section": "Common Moves",
    "name": "<td class=\"frame_fixed_m__icTnd frame_skill__tLJuM\"><span class=\"frame_arts__ZU5YI\">Backward Dash</span><p class=\"frame_classic___gpLR\"><img alt=\"\" src=\"assets/images/icons/key-l.png\"/><img alt=\"\" src=\"assets/images/icons/key-l.png\"/></p></td>",
    "startup": "<td class=\"frame_startup_frame__Dc2Ph\"></td>",
    "active": "<td class=\"frame_active_frame__6Sovc\"></td>",
    "recovery": "<td class=\"frame_recovery_frame__CznJj\">25 total frames</td>",
    "hitAdv": "<td class=\"frame_hit_frame__K7xOz\"></td>",
    "guardAdv": "<td class=\"frame_block_frame__SfHiW\"></td>",
    "cancel": "<td class=\"frame_cancel__hT_hr\"></td>",
    "damage": "<td class=\"frame_damage__HWaQm\">0 </td>",
    "comboMod": "<td class=\"frame_combo_correct__hCDUB\"></td>",
    "driveGain": "<td class=\"frame_drive_gauge_gain_hit___Jg7j\">0</td>",
    "driveLossGuard": "<td class=\"frame_drive_gauge_lose_dguard__4uQOc\">0</td>",
    "driveLossPunish": "<td class=\"frame_drive_gauge_lose_punish__mFrmM\">0</td>",
    "saGain": "<td class=\"frame_sa_gauge_gain__oGcqw\">0</td>",
    "attribute": "<td class=\"frame_attribute__1vABD\"></td>",
    "notes": "<td class=\"frame_note__hfwBr\"><p>Invincible to throws from frame 1 to frame 15.</p></td>"
  },
  {
    "section": "Common Moves",
    "name": "<td class=\"frame_fixed_m__icTnd frame_skill__tLJuM\"><span class=\"frame_arts__ZU5YI\">Drive Impact: Glissade</span><p class=\"frame_classic___gpLR\"><img alt=\"\" src=\"assets/images/icons/icon_punch_h.png\"/>H<img alt=\"\" src=\"assets/images/icons/icon_kick_h.png\"/>H</p></td>",
    "startup": "<td class=\"frame_startup_frame__Dc2Ph\">26</td>",
    "active": "<td class=\"frame_active_frame__6Sovc\"><p>26-27</p></td>",
    "recovery": "<td class=\"frame_recovery_frame__CznJj\">35</td>",
    "hitAdv": "<td class=\"frame_hit_frame__K7xOz\">D</td>",
    "guardAdv": "<td class=\"frame_block_frame__SfHiW undefined\">-3</td>",
    "cancel": "<td class=\"frame_cancel__hT_hr\"></td>",
    "damage": "<td class=\"frame_damage__HWaQm\">800 </td>",
    "comboMod": "<td class=\"frame_combo_correct__hCDUB\">Starter scaling 20%<br/></td>",
    "driveGain": "<td class=\"frame_drive_gauge_gain_hit___Jg7j\">800</td>",
    "driveLossGuard": "<td class=\"frame_drive_gauge_lose_dguard__4uQOc\">-5000</td>",
    "driveLossPunish": "<td class=\"frame_drive_gauge_lose_punish__mFrmM\">-15000</td>",
    "saGain": "<td class=\"frame_sa_gauge_gain__oGcqw\">0</td>",
    "attribute": "<td class=\"frame_attribute__1vABD\">High</td>",
    "notes": "<td class=\"frame_note__hfwBr\"><p>Super Armor for 2 attacks from frames 1 - 27<br/>Produces a wall splat if the pushback on hit causes the opponent to connect with the stage wall<br/>On Punish Counter or after a successful hit after Super Armor absorbs a hit, the following properties change:<br/>- Produces a crumple stun if the opponent is standing on the ground<br/>- Juggle state time is increased if the opponent is in the air<br/>- Super Art gauge increases by 3000</p></td>"
  },
  {
    "section": "Common Moves",
    "name": "<td class=\"frame_fixed_m__icTnd frame_skill__tLJuM\"><span class=\"frame_arts__ZU5YI\">Drive Reversal (while blocking): Écarté</span><p class=\"frame_classic___gpLR\">(When blocking or during a successful Drive Parry)<img alt=\"\" src=\"assets/images/icons/key-r.png\"/> <img alt=\"\" src=\"assets/images/icons/key-plus.png\"/> <img alt=\"\" src=\"assets/images/icons/icon_punch_h.png\"/>H<img alt=\"\" src=\"assets/images/icons/icon_kick_h.png\"/>H</p></td>",
    "startup": "<td class=\"frame_startup_frame__Dc2Ph\">20</td>",
    "active": "<td class=\"frame_active_frame__6Sovc\"><p>20-22</p></td>",
    "recovery": "<td class=\"frame_recovery_frame__CznJj\">26</td>",
    "hitAdv": "<td class=\"frame_hit_frame__K7xOz\">D</td>",
    "guardAdv": "<td class=\"frame_block_frame__SfHiW undefined\">-6</td>",
    "cancel": "<td class=\"frame_cancel__hT_hr\"></td>",
    "damage": "<td class=\"frame_damage__HWaQm\">0 </td>",
    "comboMod": "<td class=\"frame_combo_correct__hCDUB\"></td>",
    "driveGain": "<td class=\"frame_drive_gauge_gain_hit___Jg7j\">500</td>",
    "driveLossGuard": "<td class=\"frame_drive_gauge_lose_dguard__4uQOc\">0</td>",
    "driveLossPunish": "<td class=\"frame_drive_gauge_lose_punish__mFrmM\">0</td>",
    "saGain": "<td class=\"frame_sa_gauge_gain__oGcqw\">0</td>",
    "attribute": "<td class=\"frame_attribute__1vABD\">High</td>",
    "notes": "<td class=\"frame_note__hfwBr\"><p>Recoverable damage<br/>Completely invincible from frames 1 - 22<br/>5 frames of recovery added on hit</p></td>"
  },
  {
    "section": "Common Moves",
    "name": "<td class=\"frame_fixed_m__icTnd frame_skill__tLJuM\"><span class=\"frame_arts__ZU5YI\">Drive Reversal (while recovering): Écarté</span><p class=\"frame_classic___gpLR\">(During knockdown recovery)<img alt=\"\" src=\"assets/images/icons/key-r.png\"/> <img alt=\"\" src=\"assets/images/icons/key-plus.png\"/> <img alt=\"\" src=\"assets/images/icons/icon_punch_h.png\"/>H<img alt=\"\" src=\"assets/images/icons/icon_kick_h.png\"/>H</p></td>",
    "startup": "<td class=\"frame_startup_frame__Dc2Ph\">18</td>",
    "active": "<td class=\"frame_active_frame__6Sovc\"><p>18-20</p></td>",
    "recovery": "<td class=\"frame_recovery_frame__CznJj\">26</td>",
    "hitAdv": "<td class=\"frame_hit_frame__K7xOz\">D</td>",
    "guardAdv": "<td class=\"frame_block_frame__SfHiW undefined\">-6</td>",
    "cancel": "<td class=\"frame_cancel__hT_hr\"></td>",
    "damage": "<td class=\"frame_damage__HWaQm\">500 </td>",
    "comboMod": "<td class=\"frame_combo_correct__hCDUB\"></td>",
    "driveGain": "<td class=\"frame_drive_gauge_gain_hit___Jg7j\">0</td>",
    "driveLossGuard": "<td class=\"frame_drive_gauge_lose_dguard__4uQOc\">0</td>",
    "driveLossPunish": "<td class=\"frame_drive_gauge_lose_punish__mFrmM\">0</td>",
    "saGain": "<td class=\"frame_sa_gauge_gain__oGcqw\">0</td>",
    "attribute": "<td class=\"frame_attribute__1vABD\">High</td>",
    "notes": "<td class=\"frame_note__hfwBr\"><p>Recoverable damage<br/>Completely invincible on frames 1 - 20<br/>5 frames of recovery added on hit</p></td>"
  },
  {
    "section": "Common Moves",
    "name": "<td class=\"frame_fixed_m__icTnd frame_skill__tLJuM\"><span class=\"frame_arts__ZU5YI\">Drive Parry</span><p class=\"frame_classic___gpLR\"><img alt=\"\" src=\"assets/images/icons/icon_punch_m.png\"/>M<img alt=\"\" src=\"assets/images/icons/icon_kick_m.png\"/>M</p></td>",
    "startup": "<td class=\"frame_startup_frame__Dc2Ph\">1</td>",
    "active": "<td class=\"frame_active_frame__6Sovc\"><p>[*2] 1-12</p></td>",
    "recovery": "<td class=\"frame_recovery_frame__CznJj\">33</td>",
    "hitAdv": "<td class=\"frame_hit_frame__K7xOz\"></td>",
    "guardAdv": "<td class=\"frame_block_frame__SfHiW\"></td>",
    "cancel": "<td class=\"frame_cancel__hT_hr\"><span>*1</span></td>",
    "damage": "<td class=\"frame_damage__HWaQm\">0 </td>",
    "comboMod": "<td class=\"frame_combo_correct__hCDUB\"></td>",
    "driveGain": "<td class=\"frame_drive_gauge_gain_hit___Jg7j\">0</td>",
    "driveLossGuard": "<td class=\"frame_drive_gauge_lose_dguard__4uQOc\">0</td>",
    "driveLossPunish": "<td class=\"frame_drive_gauge_lose_punish__mFrmM\">0</td>",
    "saGain": "<td class=\"frame_sa_gauge_gain__oGcqw\">0</td>",
    "attribute": "<td class=\"frame_attribute__1vABD\"></td>",
    "notes": "<td class=\"frame_note__hfwBr\"><p>*1 Can be canceled from the 4th frame via Drive Rush<br/>*2 Parry hitbox is extended for as long as the buttons are held<br/>Only blocks can be performed during the recovery period<br/>Always in Punish Counter state during execution.</p></td>"
  },
  {
    "section": "Common Moves",
    "name": "<td class=\"frame_fixed_m__icTnd frame_skill__tLJuM\"><span class=\"frame_arts__ZU5YI\">Perfect Parry (strike)</span><p class=\"frame_classic___gpLR\">Block Direction <img alt=\"\" src=\"assets/images/icons/key-plus.png\"/> <img alt=\"\" src=\"assets/images/icons/icon_punch_m.png\"/>M<img alt=\"\" src=\"assets/images/icons/icon_kick_m.png\"/>M</p></td>",
    "startup": "<td class=\"frame_startup_frame__Dc2Ph\">1</td>",
    "active": "<td class=\"frame_active_frame__6Sovc\"></td>",
    "recovery": "<td class=\"frame_recovery_frame__CznJj\">1</td>",
    "hitAdv": "<td class=\"frame_hit_frame__K7xOz\"></td>",
    "guardAdv": "<td class=\"frame_block_frame__SfHiW\"></td>",
    "cancel": "<td class=\"frame_cancel__hT_hr\"></td>",
    "damage": "<td class=\"frame_damage__HWaQm\">0 </td>",
    "comboMod": "<td class=\"frame_combo_correct__hCDUB\">Starter scaling 50％<br/></td>",
    "driveGain": "<td class=\"frame_drive_gauge_gain_hit___Jg7j\"></td>",
    "driveLossGuard": "<td class=\"frame_drive_gauge_lose_dguard__4uQOc\"></td>",
    "driveLossPunish": "<td class=\"frame_drive_gauge_lose_punish__mFrmM\"></td>",
    "saGain": "<td class=\"frame_sa_gauge_gain__oGcqw\"></td>",
    "attribute": "<td class=\"frame_attribute__1vABD\"></td>",
    "notes": "<td class=\"frame_note__hfwBr\"><p>Perfect Parry activates when an attack is absorbed on the frame a parry is input, or on the next frame. (For high and overhead attacks, the player must press the direction away from the opponent. For low attacks, down and back)<br/>If no direction is inputted the result will be a regular parry with an additional Drive increase of 3000.<br/>Fully invincible for 5 frames once recovery is over (invincibility not granted if you continue the parry)<br/>The player on the receiving end of a Perfect Parry cannot cancel and is forced into a Punish Counter state until their move is finished</p></td>"
  },
  {
    "section": "Common Moves",
    "name": "<td class=\"frame_fixed_m__icTnd frame_skill__tLJuM\"><span class=\"frame_arts__ZU5YI\">Perfect Parry (projectile)</span><p class=\"frame_classic___gpLR\"><img alt=\"\" src=\"assets/images/icons/icon_punch_m.png\"/>M<img alt=\"\" src=\"assets/images/icons/icon_kick_m.png\"/>M</p></td>",
    "startup": "<td class=\"frame_startup_frame__Dc2Ph\">1</td>",
    "active": "<td class=\"frame_active_frame__6Sovc\"></td>",
    "recovery": "<td class=\"frame_recovery_frame__CznJj\">10</td>",
    "hitAdv": "<td class=\"frame_hit_frame__K7xOz\"></td>",
    "guardAdv": "<td class=\"frame_block_frame__SfHiW\"></td>",
    "cancel": "<td class=\"frame_cancel__hT_hr\"></td>",
    "damage": "<td class=\"frame_damage__HWaQm\">0 </td>",
    "comboMod": "<td class=\"frame_combo_correct__hCDUB\">Starter scaling 50％<br/></td>",
    "driveGain": "<td class=\"frame_drive_gauge_gain_hit___Jg7j\"></td>",
    "driveLossGuard": "<td class=\"frame_drive_gauge_lose_dguard__4uQOc\"></td>",
    "driveLossPunish": "<td class=\"frame_drive_gauge_lose_punish__mFrmM\"></td>",
    "saGain": "<td class=\"frame_sa_gauge_gain__oGcqw\"></td>",
    "attribute": "<td class=\"frame_attribute__1vABD\"></td>",
    "notes": "<td class=\"frame_note__hfwBr\"><p>Perfect Parry activates when an attack is absorbed on the frame a parry is input, or on the next frame<br/>No screen freeze occurs.<br/>The player on the receiving end of a Perfect Parry cannot cancel and is forced into a Punish Counter state until their move is finished</p></td>"
  },
  {
    "section": "Common Moves",
    "name": "<td class=\"frame_fixed_m__icTnd frame_skill__tLJuM\"><span class=\"frame_arts__ZU5YI\">Parry Drive Rush</span><p class=\"frame_classic___gpLR\">(During a Drive Parry)<img alt=\"\" src=\"assets/images/icons/key-r.png\"/><img alt=\"\" src=\"assets/images/icons/key-r.png\"/></p></td>",
    "startup": "<td class=\"frame_startup_frame__Dc2Ph\"></td>",
    "active": "<td class=\"frame_active_frame__6Sovc\"></td>",
    "recovery": "<td class=\"frame_recovery_frame__CznJj\">45 total frames</td>",
    "hitAdv": "<td class=\"frame_hit_frame__K7xOz\"></td>",
    "guardAdv": "<td class=\"frame_block_frame__SfHiW\"></td>",
    "cancel": "<td class=\"frame_cancel__hT_hr\"><span>*</span></td>",
    "damage": "<td class=\"frame_damage__HWaQm\">0 </td>",
    "comboMod": "<td class=\"frame_combo_correct__hCDUB\">Multiplier scaling 15％<br/></td>",
    "driveGain": "<td class=\"frame_drive_gauge_gain_hit___Jg7j\">0</td>",
    "driveLossGuard": "<td class=\"frame_drive_gauge_lose_dguard__4uQOc\">0</td>",
    "driveLossPunish": "<td class=\"frame_drive_gauge_lose_punish__mFrmM\">0</td>",
    "saGain": "<td class=\"frame_sa_gauge_gain__oGcqw\">0</td>",
    "attribute": "<td class=\"frame_attribute__1vABD\"></td>",
    "notes": "<td class=\"frame_note__hfwBr\"><p>Screen freeze occurs until the 10th frame<br/>* Can be canceled into an attack on the 9th frame of the move<br/>   Can be canceled into actions other than a parry from the 24th frame</p></td>"
  },
  {
    "section": "Common Moves",
    "name": "<td class=\"frame_fixed_m__icTnd frame_skill__tLJuM\"><span class=\"frame_arts__ZU5YI\">Cancel Drive Rush</span><p class=\"frame_classic___gpLR\">(While connecting with a special-cancelable move)<img alt=\"\" src=\"assets/images/icons/key-r.png\"/><img alt=\"\" src=\"assets/images/icons/key-r.png\"/> <img alt=\"\" src=\"assets/images/icons/key-or.png\"/> (<img alt=\"\" src=\"assets/images/icons/key-nutral.png\"/> <img alt=\"\" src=\"assets/images/icons/key-or.png\"/> <img alt=\"\" src=\"assets/images/icons/key-r.png\"/>) <img alt=\"\" src=\"assets/images/icons/key-plus.png\"/> <img alt=\"\" src=\"assets/images/icons/icon_punch_m.png\"/>M<img alt=\"\" src=\"assets/images/icons/icon_kick_m.png\"/>M</p></td>",
    "startup": "<td class=\"frame_startup_frame__Dc2Ph\"></td>",
    "active": "<td class=\"frame_active_frame__6Sovc\"></td>",
    "recovery": "<td class=\"frame_recovery_frame__CznJj\">46 total frames</td>",
    "hitAdv": "<td class=\"frame_hit_frame__K7xOz\"></td>",
    "guardAdv": "<td class=\"frame_block_frame__SfHiW\"></td>",
    "cancel": "<td class=\"frame_cancel__hT_hr\"><span>*</span></td>",
    "damage": "<td class=\"frame_damage__HWaQm\">0 </td>",
    "comboMod": "<td class=\"frame_combo_correct__hCDUB\">Multiplier scaling 15％<br/></td>",
    "driveGain": "<td class=\"frame_drive_gauge_gain_hit___Jg7j\">0</td>",
    "driveLossGuard": "<td class=\"frame_drive_gauge_lose_dguard__4uQOc\">0</td>",
    "driveLossPunish": "<td class=\"frame_drive_gauge_lose_punish__mFrmM\">0</td>",
    "saGain": "<td class=\"frame_sa_gauge_gain__oGcqw\">0</td>",
    "attribute": "<td class=\"frame_attribute__1vABD\"></td>",
    "notes": "<td class=\"frame_note__hfwBr\"><p>Screen freeze occurs until the 9th frame<br/>* Can be canceled into an attack from the 10th frame of the move<br/>   Can be canceled into actions other than a parry from the 25th frame</p></td>"
  }
]